{
  "hash": "4117b96ef4a365a12d2d06d5b30030cd",
  "result": {
    "markdown": "---\ntitle: \"Lab-14: You're are Nothing but a Pack of Cards!!\"\nsubtitle: \"Making a website to show it all\"\nsummary: \"Making a website to show it all\"\nauthor: \"Arvind Venkatadri\"\ndate: \"2023-05-16\"\norder: 140\nformat: html\nlinks:\n- icon: magic\n  icon_pack: fas\n  name: slides\n  url: \"slides/14-xaringan-story/xaringan-story.html\"\n- icon: presentation\n  icon_pack: fas\n  name: ppt\n  url: \"slides/14-xaringan-story/xs.md\"\n---\n\n\n![](featured.jpg)\n\n## Introduction\n\nLet's make a website in RStudio to show off our data viz portfolio, and\nto share with friends, parents, prospective employers...\n\nWe will encounter a new package called `blogdown` and use workflows with\n[github](https://github.com) and a free web hosting service called\n[Netlify](https://www.netlify.app) to create a website where all our\nRMarkdowns become individual blog posts, complete with Titles, Sections,\nText, Diagrams and Links!\n\nNOTE: Need to update this to Quarto!!!\n\n## References\n\n1.  Allison Hill\n\n2.  Sharon Macliss\n\n3.  Yihui Xie\n",
    "supporting": [
      "index_files"
    ],
    "filters": [
      "rmarkdown/pagebreak.lua"
    ],
    "includes": {
      "include-in-header": [
        "<link href=\"../../../../../site_libs/pagedtable-1.1/css/pagedtable.css\" rel=\"stylesheet\" />\r\n<script src=\"../../../../../site_libs/pagedtable-1.1/js/pagedtable.js\"></script>\r\n"
      ]
    },
    "engineDependencies": {},
    "preserve": {},
    "postProcess": true
  }
}