{
  "hash": "dcc7daf3bc4e6958654da0a804ae9f4d",
  "result": {
    "markdown": "---\ntitle: 'Lab-7: The Lobster Quadrille'\nsubtitle: 'Fonts and other Wizardy in ggplot'\nsummary: 'Fonts and other Wizardy in ggplot'\ndate: 21/July/2021\ndate-modified: \"2023-11-21\"\nimage: featured.jpg\norder: 70\nview: 2\nformat: html\n---\n\n\n![](featured.jpg)\n\n## Introduction\n\nWe will add icing and froth to our vanilla ggplots: fonts, annotations,\nhighlights and even pictures!!\n\n## Goals\n\n-   Appreciate that a publication-worth graphic takes a lot of work!!\n-   Adding annotations, pictures and references to graphs is necessary\n    for good understanding\n-   Judicious use of colour and scales can enhance comprehension.\n\n## Pedagogical Note\n\nThe method followed will be based on\n[PRIMM](https://blogs.kcl.ac.uk/cser/2017/09/01/primm-a-structured-approach-to-teaching-programming/):\n\n-   **PREDICT** Inspect the code and guess at what the code might do,\n    **write predictions**\n-   **RUN** the code provided and check what happens\n-   **INFER** what the `parameters` of the code do and **write comments\n    to explain**. What bells and whistles can you see?\n-   **MODIFY** the `parameters` code provided to understand the\n    `options` available. **Write comments** to show what you have aimed\n    for and achieved.\n-   **MAKE** : take an idea/concept of your own, and graph it.\n\nLet's load up a few packages that we need to start:\n\n\n::: {.cell hash='index_cache/html/setup_37d2b390fcb58910c4363ae92b062717'}\n\n````{.cell-code}\n```{{r}}\n#| label: setup\n#| message: false\n## packages\nlibrary(tidyverse)   ## data science package collection (incl. the ggplot2 package)\nlibrary(systemfonts) ## use custom fonts (need to be installed on your OS)  \nlibrary(paletteer)   ## scico  and many other colour palettes palettes(http://www.fabiocrameri.ch/colourmaps.php) in R \nlibrary(ggtext)      ## add improved text rendering to ggplot2\nlibrary(ggforce)     ## add missing functionality to ggplot2\nlibrary(concaveman)  ## Needed by ggforce for plot annotation hulls\nlibrary(ggdist)      ## add uncertainty visualizations to ggplot2\nlibrary(ggformula)   ## Formula interface to ggplot\nlibrary(magick)      ## load images into R\nlibrary(patchwork)   ## combine outputs from ggplot2\nlibrary(palmerpenguins)\n\nlibrary(showtext)   ## add google fonts to plots\n\nknitr::opts_chunk$set(\n  error = TRUE,\n  comment = NA,\n  warning = FALSE,\n  errors = FALSE,\n  message = FALSE,\n  tidy = FALSE,\n  cache = FALSE,\n  echo = TRUE,\n  warning = FALSE,\n# from the vignette for the showtext package\n  fig.showtext = TRUE,\n  fig.retina = 1,\n  fig.path = \"figs/\"\n  # fig.height = 3.09,\n  # fig.width = 5\n)\n```\n````\n:::\n\n\n### Using Google Fonts\n\nWe will want to add a few new fonts to our graphs. The best way\n(currently) is to use the `showtext` package (which we loaded above) to\nbring into our work fonts from Google. To view and select the fonts you\nmight want to work with, spend some time looking over:\n\n1.  [Google Webfonts Helper\n    App](https://google-webfonts-helper.herokuapp.com/fonts)\n\n2.  [Google Fonts](https://fonts.google.com/)\n\n\n::: {.cell hash='index_cache/html/add_fonts_65ae43dab5d94028155e444ed705f4a2'}\n\n````{.cell-code}\n```{{r}}\n#| label: add_fonts\nlibrary(sysfonts)\nlibrary(showtext)\n\nsysfonts::font_add_google(\"Roboto\", \"roboto\")\nfont_add_google(\"Noto Sans\", \"noto\")\nfont_add_google(\"Open Sans\", \"open\")\nfont_add_google(\"Anton\", \"anton\")\nfont_add_google(\"Tangerine\", \"tangerine\")\n\n # set the google fonts as default\nshowtext::showtext_auto(enable = TRUE)\n```\n````\n:::\n\n::: {.cell hash='index_cache/html/Extra Pedagogical Packages_fc95ef65493796ae467ad03b2153a10e'}\n\n:::\n\n\nWe will work with a **familiar** dataset, so that we can concentrate on\nthe chart aesthetics, without having to spend time getting used to the\ndata: the `penguins` dataset again, from the `palmerpenguins` package.\n\n::: callout-tip\n## `ggformula` and `ggplot` worlds do intersect!\n\nIt seems we can mix \\`ggformula\\` code with \\`ggtext\\` code, using the\n\\`+\\` sign!! What joy !!! Need to find out if this works for other\n\\`ggplot\\` extensions as well !!!\n:::\n\n## Data\n\nAlways start your work with a **table** of the data:\n\n\n::: {.cell hash='index_cache/html/data_585584c933b7de25315cac1fcec3e930'}\n\n````{.cell-code}\n```{{r data}}\npenguins <- penguins %>% drop_na() \n# remove data containing missing data\npenguins \n```\n````\n\n::: {.cell-output-display}\n`````{=html}\n<div data-pagedtable=\"false\">\n  <script data-pagedtable-source type=\"application/json\">\n{\"columns\":[{\"label\":[\"species\"],\"name\":[1],\"type\":[\"fct\"],\"align\":[\"left\"]},{\"label\":[\"island\"],\"name\":[2],\"type\":[\"fct\"],\"align\":[\"left\"]},{\"label\":[\"bill_length_mm\"],\"name\":[3],\"type\":[\"dbl\"],\"align\":[\"right\"]},{\"label\":[\"bill_depth_mm\"],\"name\":[4],\"type\":[\"dbl\"],\"align\":[\"right\"]},{\"label\":[\"flipper_length_mm\"],\"name\":[5],\"type\":[\"int\"],\"align\":[\"right\"]},{\"label\":[\"body_mass_g\"],\"name\":[6],\"type\":[\"int\"],\"align\":[\"right\"]},{\"label\":[\"sex\"],\"name\":[7],\"type\":[\"fct\"],\"align\":[\"left\"]},{\"label\":[\"year\"],\"name\":[8],\"type\":[\"int\"],\"align\":[\"right\"]}],\"data\":[{\"1\":\"Adelie\",\"2\":\"Torgersen\",\"3\":\"39.1\",\"4\":\"18.7\",\"5\":\"181\",\"6\":\"3750\",\"7\":\"male\",\"8\":\"2007\"},{\"1\":\"Adelie\",\"2\":\"Torgersen\",\"3\":\"39.5\",\"4\":\"17.4\",\"5\":\"186\",\"6\":\"3800\",\"7\":\"female\",\"8\":\"2007\"},{\"1\":\"Adelie\",\"2\":\"Torgersen\",\"3\":\"40.3\",\"4\":\"18.0\",\"5\":\"195\",\"6\":\"3250\",\"7\":\"female\",\"8\":\"2007\"},{\"1\":\"Adelie\",\"2\":\"Torgersen\",\"3\":\"36.7\",\"4\":\"19.3\",\"5\":\"193\",\"6\":\"3450\",\"7\":\"female\",\"8\":\"2007\"},{\"1\":\"Adelie\",\"2\":\"Torgersen\",\"3\":\"39.3\",\"4\":\"20.6\",\"5\":\"190\",\"6\":\"3650\",\"7\":\"male\",\"8\":\"2007\"},{\"1\":\"Adelie\",\"2\":\"Torgersen\",\"3\":\"38.9\",\"4\":\"17.8\",\"5\":\"181\",\"6\":\"3625\",\"7\":\"female\",\"8\":\"2007\"},{\"1\":\"Adelie\",\"2\":\"Torgersen\",\"3\":\"39.2\",\"4\":\"19.6\",\"5\":\"195\",\"6\":\"4675\",\"7\":\"male\",\"8\":\"2007\"},{\"1\":\"Adelie\",\"2\":\"Torgersen\",\"3\":\"41.1\",\"4\":\"17.6\",\"5\":\"182\",\"6\":\"3200\",\"7\":\"female\",\"8\":\"2007\"},{\"1\":\"Adelie\",\"2\":\"Torgersen\",\"3\":\"38.6\",\"4\":\"21.2\",\"5\":\"191\",\"6\":\"3800\",\"7\":\"male\",\"8\":\"2007\"},{\"1\":\"Adelie\",\"2\":\"Torgersen\",\"3\":\"34.6\",\"4\":\"21.1\",\"5\":\"198\",\"6\":\"4400\",\"7\":\"male\",\"8\":\"2007\"},{\"1\":\"Adelie\",\"2\":\"Torgersen\",\"3\":\"36.6\",\"4\":\"17.8\",\"5\":\"185\",\"6\":\"3700\",\"7\":\"female\",\"8\":\"2007\"},{\"1\":\"Adelie\",\"2\":\"Torgersen\",\"3\":\"38.7\",\"4\":\"19.0\",\"5\":\"195\",\"6\":\"3450\",\"7\":\"female\",\"8\":\"2007\"},{\"1\":\"Adelie\",\"2\":\"Torgersen\",\"3\":\"42.5\",\"4\":\"20.7\",\"5\":\"197\",\"6\":\"4500\",\"7\":\"male\",\"8\":\"2007\"},{\"1\":\"Adelie\",\"2\":\"Torgersen\",\"3\":\"34.4\",\"4\":\"18.4\",\"5\":\"184\",\"6\":\"3325\",\"7\":\"female\",\"8\":\"2007\"},{\"1\":\"Adelie\",\"2\":\"Torgersen\",\"3\":\"46.0\",\"4\":\"21.5\",\"5\":\"194\",\"6\":\"4200\",\"7\":\"male\",\"8\":\"2007\"},{\"1\":\"Adelie\",\"2\":\"Biscoe\",\"3\":\"37.8\",\"4\":\"18.3\",\"5\":\"174\",\"6\":\"3400\",\"7\":\"female\",\"8\":\"2007\"},{\"1\":\"Adelie\",\"2\":\"Biscoe\",\"3\":\"37.7\",\"4\":\"18.7\",\"5\":\"180\",\"6\":\"3600\",\"7\":\"male\",\"8\":\"2007\"},{\"1\":\"Adelie\",\"2\":\"Biscoe\",\"3\":\"35.9\",\"4\":\"19.2\",\"5\":\"189\",\"6\":\"3800\",\"7\":\"female\",\"8\":\"2007\"},{\"1\":\"Adelie\",\"2\":\"Biscoe\",\"3\":\"38.2\",\"4\":\"18.1\",\"5\":\"185\",\"6\":\"3950\",\"7\":\"male\",\"8\":\"2007\"},{\"1\":\"Adelie\",\"2\":\"Biscoe\",\"3\":\"38.8\",\"4\":\"17.2\",\"5\":\"180\",\"6\":\"3800\",\"7\":\"male\",\"8\":\"2007\"},{\"1\":\"Adelie\",\"2\":\"Biscoe\",\"3\":\"35.3\",\"4\":\"18.9\",\"5\":\"187\",\"6\":\"3800\",\"7\":\"female\",\"8\":\"2007\"},{\"1\":\"Adelie\",\"2\":\"Biscoe\",\"3\":\"40.6\",\"4\":\"18.6\",\"5\":\"183\",\"6\":\"3550\",\"7\":\"male\",\"8\":\"2007\"},{\"1\":\"Adelie\",\"2\":\"Biscoe\",\"3\":\"40.5\",\"4\":\"17.9\",\"5\":\"187\",\"6\":\"3200\",\"7\":\"female\",\"8\":\"2007\"},{\"1\":\"Adelie\",\"2\":\"Biscoe\",\"3\":\"37.9\",\"4\":\"18.6\",\"5\":\"172\",\"6\":\"3150\",\"7\":\"female\",\"8\":\"2007\"},{\"1\":\"Adelie\",\"2\":\"Biscoe\",\"3\":\"40.5\",\"4\":\"18.9\",\"5\":\"180\",\"6\":\"3950\",\"7\":\"male\",\"8\":\"2007\"},{\"1\":\"Adelie\",\"2\":\"Dream\",\"3\":\"39.5\",\"4\":\"16.7\",\"5\":\"178\",\"6\":\"3250\",\"7\":\"female\",\"8\":\"2007\"},{\"1\":\"Adelie\",\"2\":\"Dream\",\"3\":\"37.2\",\"4\":\"18.1\",\"5\":\"178\",\"6\":\"3900\",\"7\":\"male\",\"8\":\"2007\"},{\"1\":\"Adelie\",\"2\":\"Dream\",\"3\":\"39.5\",\"4\":\"17.8\",\"5\":\"188\",\"6\":\"3300\",\"7\":\"female\",\"8\":\"2007\"},{\"1\":\"Adelie\",\"2\":\"Dream\",\"3\":\"40.9\",\"4\":\"18.9\",\"5\":\"184\",\"6\":\"3900\",\"7\":\"male\",\"8\":\"2007\"},{\"1\":\"Adelie\",\"2\":\"Dream\",\"3\":\"36.4\",\"4\":\"17.0\",\"5\":\"195\",\"6\":\"3325\",\"7\":\"female\",\"8\":\"2007\"},{\"1\":\"Adelie\",\"2\":\"Dream\",\"3\":\"39.2\",\"4\":\"21.1\",\"5\":\"196\",\"6\":\"4150\",\"7\":\"male\",\"8\":\"2007\"},{\"1\":\"Adelie\",\"2\":\"Dream\",\"3\":\"38.8\",\"4\":\"20.0\",\"5\":\"190\",\"6\":\"3950\",\"7\":\"male\",\"8\":\"2007\"},{\"1\":\"Adelie\",\"2\":\"Dream\",\"3\":\"42.2\",\"4\":\"18.5\",\"5\":\"180\",\"6\":\"3550\",\"7\":\"female\",\"8\":\"2007\"},{\"1\":\"Adelie\",\"2\":\"Dream\",\"3\":\"37.6\",\"4\":\"19.3\",\"5\":\"181\",\"6\":\"3300\",\"7\":\"female\",\"8\":\"2007\"},{\"1\":\"Adelie\",\"2\":\"Dream\",\"3\":\"39.8\",\"4\":\"19.1\",\"5\":\"184\",\"6\":\"4650\",\"7\":\"male\",\"8\":\"2007\"},{\"1\":\"Adelie\",\"2\":\"Dream\",\"3\":\"36.5\",\"4\":\"18.0\",\"5\":\"182\",\"6\":\"3150\",\"7\":\"female\",\"8\":\"2007\"},{\"1\":\"Adelie\",\"2\":\"Dream\",\"3\":\"40.8\",\"4\":\"18.4\",\"5\":\"195\",\"6\":\"3900\",\"7\":\"male\",\"8\":\"2007\"},{\"1\":\"Adelie\",\"2\":\"Dream\",\"3\":\"36.0\",\"4\":\"18.5\",\"5\":\"186\",\"6\":\"3100\",\"7\":\"female\",\"8\":\"2007\"},{\"1\":\"Adelie\",\"2\":\"Dream\",\"3\":\"44.1\",\"4\":\"19.7\",\"5\":\"196\",\"6\":\"4400\",\"7\":\"male\",\"8\":\"2007\"},{\"1\":\"Adelie\",\"2\":\"Dream\",\"3\":\"37.0\",\"4\":\"16.9\",\"5\":\"185\",\"6\":\"3000\",\"7\":\"female\",\"8\":\"2007\"},{\"1\":\"Adelie\",\"2\":\"Dream\",\"3\":\"39.6\",\"4\":\"18.8\",\"5\":\"190\",\"6\":\"4600\",\"7\":\"male\",\"8\":\"2007\"},{\"1\":\"Adelie\",\"2\":\"Dream\",\"3\":\"41.1\",\"4\":\"19.0\",\"5\":\"182\",\"6\":\"3425\",\"7\":\"male\",\"8\":\"2007\"},{\"1\":\"Adelie\",\"2\":\"Dream\",\"3\":\"36.0\",\"4\":\"17.9\",\"5\":\"190\",\"6\":\"3450\",\"7\":\"female\",\"8\":\"2007\"},{\"1\":\"Adelie\",\"2\":\"Dream\",\"3\":\"42.3\",\"4\":\"21.2\",\"5\":\"191\",\"6\":\"4150\",\"7\":\"male\",\"8\":\"2007\"},{\"1\":\"Adelie\",\"2\":\"Biscoe\",\"3\":\"39.6\",\"4\":\"17.7\",\"5\":\"186\",\"6\":\"3500\",\"7\":\"female\",\"8\":\"2008\"},{\"1\":\"Adelie\",\"2\":\"Biscoe\",\"3\":\"40.1\",\"4\":\"18.9\",\"5\":\"188\",\"6\":\"4300\",\"7\":\"male\",\"8\":\"2008\"},{\"1\":\"Adelie\",\"2\":\"Biscoe\",\"3\":\"35.0\",\"4\":\"17.9\",\"5\":\"190\",\"6\":\"3450\",\"7\":\"female\",\"8\":\"2008\"},{\"1\":\"Adelie\",\"2\":\"Biscoe\",\"3\":\"42.0\",\"4\":\"19.5\",\"5\":\"200\",\"6\":\"4050\",\"7\":\"male\",\"8\":\"2008\"},{\"1\":\"Adelie\",\"2\":\"Biscoe\",\"3\":\"34.5\",\"4\":\"18.1\",\"5\":\"187\",\"6\":\"2900\",\"7\":\"female\",\"8\":\"2008\"},{\"1\":\"Adelie\",\"2\":\"Biscoe\",\"3\":\"41.4\",\"4\":\"18.6\",\"5\":\"191\",\"6\":\"3700\",\"7\":\"male\",\"8\":\"2008\"},{\"1\":\"Adelie\",\"2\":\"Biscoe\",\"3\":\"39.0\",\"4\":\"17.5\",\"5\":\"186\",\"6\":\"3550\",\"7\":\"female\",\"8\":\"2008\"},{\"1\":\"Adelie\",\"2\":\"Biscoe\",\"3\":\"40.6\",\"4\":\"18.8\",\"5\":\"193\",\"6\":\"3800\",\"7\":\"male\",\"8\":\"2008\"},{\"1\":\"Adelie\",\"2\":\"Biscoe\",\"3\":\"36.5\",\"4\":\"16.6\",\"5\":\"181\",\"6\":\"2850\",\"7\":\"female\",\"8\":\"2008\"},{\"1\":\"Adelie\",\"2\":\"Biscoe\",\"3\":\"37.6\",\"4\":\"19.1\",\"5\":\"194\",\"6\":\"3750\",\"7\":\"male\",\"8\":\"2008\"},{\"1\":\"Adelie\",\"2\":\"Biscoe\",\"3\":\"35.7\",\"4\":\"16.9\",\"5\":\"185\",\"6\":\"3150\",\"7\":\"female\",\"8\":\"2008\"},{\"1\":\"Adelie\",\"2\":\"Biscoe\",\"3\":\"41.3\",\"4\":\"21.1\",\"5\":\"195\",\"6\":\"4400\",\"7\":\"male\",\"8\":\"2008\"},{\"1\":\"Adelie\",\"2\":\"Biscoe\",\"3\":\"37.6\",\"4\":\"17.0\",\"5\":\"185\",\"6\":\"3600\",\"7\":\"female\",\"8\":\"2008\"},{\"1\":\"Adelie\",\"2\":\"Biscoe\",\"3\":\"41.1\",\"4\":\"18.2\",\"5\":\"192\",\"6\":\"4050\",\"7\":\"male\",\"8\":\"2008\"},{\"1\":\"Adelie\",\"2\":\"Biscoe\",\"3\":\"36.4\",\"4\":\"17.1\",\"5\":\"184\",\"6\":\"2850\",\"7\":\"female\",\"8\":\"2008\"},{\"1\":\"Adelie\",\"2\":\"Biscoe\",\"3\":\"41.6\",\"4\":\"18.0\",\"5\":\"192\",\"6\":\"3950\",\"7\":\"male\",\"8\":\"2008\"},{\"1\":\"Adelie\",\"2\":\"Biscoe\",\"3\":\"35.5\",\"4\":\"16.2\",\"5\":\"195\",\"6\":\"3350\",\"7\":\"female\",\"8\":\"2008\"},{\"1\":\"Adelie\",\"2\":\"Biscoe\",\"3\":\"41.1\",\"4\":\"19.1\",\"5\":\"188\",\"6\":\"4100\",\"7\":\"male\",\"8\":\"2008\"},{\"1\":\"Adelie\",\"2\":\"Torgersen\",\"3\":\"35.9\",\"4\":\"16.6\",\"5\":\"190\",\"6\":\"3050\",\"7\":\"female\",\"8\":\"2008\"},{\"1\":\"Adelie\",\"2\":\"Torgersen\",\"3\":\"41.8\",\"4\":\"19.4\",\"5\":\"198\",\"6\":\"4450\",\"7\":\"male\",\"8\":\"2008\"},{\"1\":\"Adelie\",\"2\":\"Torgersen\",\"3\":\"33.5\",\"4\":\"19.0\",\"5\":\"190\",\"6\":\"3600\",\"7\":\"female\",\"8\":\"2008\"},{\"1\":\"Adelie\",\"2\":\"Torgersen\",\"3\":\"39.7\",\"4\":\"18.4\",\"5\":\"190\",\"6\":\"3900\",\"7\":\"male\",\"8\":\"2008\"},{\"1\":\"Adelie\",\"2\":\"Torgersen\",\"3\":\"39.6\",\"4\":\"17.2\",\"5\":\"196\",\"6\":\"3550\",\"7\":\"female\",\"8\":\"2008\"},{\"1\":\"Adelie\",\"2\":\"Torgersen\",\"3\":\"45.8\",\"4\":\"18.9\",\"5\":\"197\",\"6\":\"4150\",\"7\":\"male\",\"8\":\"2008\"},{\"1\":\"Adelie\",\"2\":\"Torgersen\",\"3\":\"35.5\",\"4\":\"17.5\",\"5\":\"190\",\"6\":\"3700\",\"7\":\"female\",\"8\":\"2008\"},{\"1\":\"Adelie\",\"2\":\"Torgersen\",\"3\":\"42.8\",\"4\":\"18.5\",\"5\":\"195\",\"6\":\"4250\",\"7\":\"male\",\"8\":\"2008\"},{\"1\":\"Adelie\",\"2\":\"Torgersen\",\"3\":\"40.9\",\"4\":\"16.8\",\"5\":\"191\",\"6\":\"3700\",\"7\":\"female\",\"8\":\"2008\"},{\"1\":\"Adelie\",\"2\":\"Torgersen\",\"3\":\"37.2\",\"4\":\"19.4\",\"5\":\"184\",\"6\":\"3900\",\"7\":\"male\",\"8\":\"2008\"},{\"1\":\"Adelie\",\"2\":\"Torgersen\",\"3\":\"36.2\",\"4\":\"16.1\",\"5\":\"187\",\"6\":\"3550\",\"7\":\"female\",\"8\":\"2008\"},{\"1\":\"Adelie\",\"2\":\"Torgersen\",\"3\":\"42.1\",\"4\":\"19.1\",\"5\":\"195\",\"6\":\"4000\",\"7\":\"male\",\"8\":\"2008\"},{\"1\":\"Adelie\",\"2\":\"Torgersen\",\"3\":\"34.6\",\"4\":\"17.2\",\"5\":\"189\",\"6\":\"3200\",\"7\":\"female\",\"8\":\"2008\"},{\"1\":\"Adelie\",\"2\":\"Torgersen\",\"3\":\"42.9\",\"4\":\"17.6\",\"5\":\"196\",\"6\":\"4700\",\"7\":\"male\",\"8\":\"2008\"},{\"1\":\"Adelie\",\"2\":\"Torgersen\",\"3\":\"36.7\",\"4\":\"18.8\",\"5\":\"187\",\"6\":\"3800\",\"7\":\"female\",\"8\":\"2008\"},{\"1\":\"Adelie\",\"2\":\"Torgersen\",\"3\":\"35.1\",\"4\":\"19.4\",\"5\":\"193\",\"6\":\"4200\",\"7\":\"male\",\"8\":\"2008\"},{\"1\":\"Adelie\",\"2\":\"Dream\",\"3\":\"37.3\",\"4\":\"17.8\",\"5\":\"191\",\"6\":\"3350\",\"7\":\"female\",\"8\":\"2008\"},{\"1\":\"Adelie\",\"2\":\"Dream\",\"3\":\"41.3\",\"4\":\"20.3\",\"5\":\"194\",\"6\":\"3550\",\"7\":\"male\",\"8\":\"2008\"},{\"1\":\"Adelie\",\"2\":\"Dream\",\"3\":\"36.3\",\"4\":\"19.5\",\"5\":\"190\",\"6\":\"3800\",\"7\":\"male\",\"8\":\"2008\"},{\"1\":\"Adelie\",\"2\":\"Dream\",\"3\":\"36.9\",\"4\":\"18.6\",\"5\":\"189\",\"6\":\"3500\",\"7\":\"female\",\"8\":\"2008\"},{\"1\":\"Adelie\",\"2\":\"Dream\",\"3\":\"38.3\",\"4\":\"19.2\",\"5\":\"189\",\"6\":\"3950\",\"7\":\"male\",\"8\":\"2008\"},{\"1\":\"Adelie\",\"2\":\"Dream\",\"3\":\"38.9\",\"4\":\"18.8\",\"5\":\"190\",\"6\":\"3600\",\"7\":\"female\",\"8\":\"2008\"},{\"1\":\"Adelie\",\"2\":\"Dream\",\"3\":\"35.7\",\"4\":\"18.0\",\"5\":\"202\",\"6\":\"3550\",\"7\":\"female\",\"8\":\"2008\"},{\"1\":\"Adelie\",\"2\":\"Dream\",\"3\":\"41.1\",\"4\":\"18.1\",\"5\":\"205\",\"6\":\"4300\",\"7\":\"male\",\"8\":\"2008\"},{\"1\":\"Adelie\",\"2\":\"Dream\",\"3\":\"34.0\",\"4\":\"17.1\",\"5\":\"185\",\"6\":\"3400\",\"7\":\"female\",\"8\":\"2008\"},{\"1\":\"Adelie\",\"2\":\"Dream\",\"3\":\"39.6\",\"4\":\"18.1\",\"5\":\"186\",\"6\":\"4450\",\"7\":\"male\",\"8\":\"2008\"},{\"1\":\"Adelie\",\"2\":\"Dream\",\"3\":\"36.2\",\"4\":\"17.3\",\"5\":\"187\",\"6\":\"3300\",\"7\":\"female\",\"8\":\"2008\"},{\"1\":\"Adelie\",\"2\":\"Dream\",\"3\":\"40.8\",\"4\":\"18.9\",\"5\":\"208\",\"6\":\"4300\",\"7\":\"male\",\"8\":\"2008\"},{\"1\":\"Adelie\",\"2\":\"Dream\",\"3\":\"38.1\",\"4\":\"18.6\",\"5\":\"190\",\"6\":\"3700\",\"7\":\"female\",\"8\":\"2008\"},{\"1\":\"Adelie\",\"2\":\"Dream\",\"3\":\"40.3\",\"4\":\"18.5\",\"5\":\"196\",\"6\":\"4350\",\"7\":\"male\",\"8\":\"2008\"},{\"1\":\"Adelie\",\"2\":\"Dream\",\"3\":\"33.1\",\"4\":\"16.1\",\"5\":\"178\",\"6\":\"2900\",\"7\":\"female\",\"8\":\"2008\"},{\"1\":\"Adelie\",\"2\":\"Dream\",\"3\":\"43.2\",\"4\":\"18.5\",\"5\":\"192\",\"6\":\"4100\",\"7\":\"male\",\"8\":\"2008\"},{\"1\":\"Adelie\",\"2\":\"Biscoe\",\"3\":\"35.0\",\"4\":\"17.9\",\"5\":\"192\",\"6\":\"3725\",\"7\":\"female\",\"8\":\"2009\"},{\"1\":\"Adelie\",\"2\":\"Biscoe\",\"3\":\"41.0\",\"4\":\"20.0\",\"5\":\"203\",\"6\":\"4725\",\"7\":\"male\",\"8\":\"2009\"},{\"1\":\"Adelie\",\"2\":\"Biscoe\",\"3\":\"37.7\",\"4\":\"16.0\",\"5\":\"183\",\"6\":\"3075\",\"7\":\"female\",\"8\":\"2009\"},{\"1\":\"Adelie\",\"2\":\"Biscoe\",\"3\":\"37.8\",\"4\":\"20.0\",\"5\":\"190\",\"6\":\"4250\",\"7\":\"male\",\"8\":\"2009\"},{\"1\":\"Adelie\",\"2\":\"Biscoe\",\"3\":\"37.9\",\"4\":\"18.6\",\"5\":\"193\",\"6\":\"2925\",\"7\":\"female\",\"8\":\"2009\"},{\"1\":\"Adelie\",\"2\":\"Biscoe\",\"3\":\"39.7\",\"4\":\"18.9\",\"5\":\"184\",\"6\":\"3550\",\"7\":\"male\",\"8\":\"2009\"},{\"1\":\"Adelie\",\"2\":\"Biscoe\",\"3\":\"38.6\",\"4\":\"17.2\",\"5\":\"199\",\"6\":\"3750\",\"7\":\"female\",\"8\":\"2009\"},{\"1\":\"Adelie\",\"2\":\"Biscoe\",\"3\":\"38.2\",\"4\":\"20.0\",\"5\":\"190\",\"6\":\"3900\",\"7\":\"male\",\"8\":\"2009\"},{\"1\":\"Adelie\",\"2\":\"Biscoe\",\"3\":\"38.1\",\"4\":\"17.0\",\"5\":\"181\",\"6\":\"3175\",\"7\":\"female\",\"8\":\"2009\"},{\"1\":\"Adelie\",\"2\":\"Biscoe\",\"3\":\"43.2\",\"4\":\"19.0\",\"5\":\"197\",\"6\":\"4775\",\"7\":\"male\",\"8\":\"2009\"},{\"1\":\"Adelie\",\"2\":\"Biscoe\",\"3\":\"38.1\",\"4\":\"16.5\",\"5\":\"198\",\"6\":\"3825\",\"7\":\"female\",\"8\":\"2009\"},{\"1\":\"Adelie\",\"2\":\"Biscoe\",\"3\":\"45.6\",\"4\":\"20.3\",\"5\":\"191\",\"6\":\"4600\",\"7\":\"male\",\"8\":\"2009\"},{\"1\":\"Adelie\",\"2\":\"Biscoe\",\"3\":\"39.7\",\"4\":\"17.7\",\"5\":\"193\",\"6\":\"3200\",\"7\":\"female\",\"8\":\"2009\"},{\"1\":\"Adelie\",\"2\":\"Biscoe\",\"3\":\"42.2\",\"4\":\"19.5\",\"5\":\"197\",\"6\":\"4275\",\"7\":\"male\",\"8\":\"2009\"},{\"1\":\"Adelie\",\"2\":\"Biscoe\",\"3\":\"39.6\",\"4\":\"20.7\",\"5\":\"191\",\"6\":\"3900\",\"7\":\"female\",\"8\":\"2009\"},{\"1\":\"Adelie\",\"2\":\"Biscoe\",\"3\":\"42.7\",\"4\":\"18.3\",\"5\":\"196\",\"6\":\"4075\",\"7\":\"male\",\"8\":\"2009\"},{\"1\":\"Adelie\",\"2\":\"Torgersen\",\"3\":\"38.6\",\"4\":\"17.0\",\"5\":\"188\",\"6\":\"2900\",\"7\":\"female\",\"8\":\"2009\"},{\"1\":\"Adelie\",\"2\":\"Torgersen\",\"3\":\"37.3\",\"4\":\"20.5\",\"5\":\"199\",\"6\":\"3775\",\"7\":\"male\",\"8\":\"2009\"},{\"1\":\"Adelie\",\"2\":\"Torgersen\",\"3\":\"35.7\",\"4\":\"17.0\",\"5\":\"189\",\"6\":\"3350\",\"7\":\"female\",\"8\":\"2009\"},{\"1\":\"Adelie\",\"2\":\"Torgersen\",\"3\":\"41.1\",\"4\":\"18.6\",\"5\":\"189\",\"6\":\"3325\",\"7\":\"male\",\"8\":\"2009\"},{\"1\":\"Adelie\",\"2\":\"Torgersen\",\"3\":\"36.2\",\"4\":\"17.2\",\"5\":\"187\",\"6\":\"3150\",\"7\":\"female\",\"8\":\"2009\"},{\"1\":\"Adelie\",\"2\":\"Torgersen\",\"3\":\"37.7\",\"4\":\"19.8\",\"5\":\"198\",\"6\":\"3500\",\"7\":\"male\",\"8\":\"2009\"},{\"1\":\"Adelie\",\"2\":\"Torgersen\",\"3\":\"40.2\",\"4\":\"17.0\",\"5\":\"176\",\"6\":\"3450\",\"7\":\"female\",\"8\":\"2009\"},{\"1\":\"Adelie\",\"2\":\"Torgersen\",\"3\":\"41.4\",\"4\":\"18.5\",\"5\":\"202\",\"6\":\"3875\",\"7\":\"male\",\"8\":\"2009\"},{\"1\":\"Adelie\",\"2\":\"Torgersen\",\"3\":\"35.2\",\"4\":\"15.9\",\"5\":\"186\",\"6\":\"3050\",\"7\":\"female\",\"8\":\"2009\"},{\"1\":\"Adelie\",\"2\":\"Torgersen\",\"3\":\"40.6\",\"4\":\"19.0\",\"5\":\"199\",\"6\":\"4000\",\"7\":\"male\",\"8\":\"2009\"},{\"1\":\"Adelie\",\"2\":\"Torgersen\",\"3\":\"38.8\",\"4\":\"17.6\",\"5\":\"191\",\"6\":\"3275\",\"7\":\"female\",\"8\":\"2009\"},{\"1\":\"Adelie\",\"2\":\"Torgersen\",\"3\":\"41.5\",\"4\":\"18.3\",\"5\":\"195\",\"6\":\"4300\",\"7\":\"male\",\"8\":\"2009\"},{\"1\":\"Adelie\",\"2\":\"Torgersen\",\"3\":\"39.0\",\"4\":\"17.1\",\"5\":\"191\",\"6\":\"3050\",\"7\":\"female\",\"8\":\"2009\"},{\"1\":\"Adelie\",\"2\":\"Torgersen\",\"3\":\"44.1\",\"4\":\"18.0\",\"5\":\"210\",\"6\":\"4000\",\"7\":\"male\",\"8\":\"2009\"},{\"1\":\"Adelie\",\"2\":\"Torgersen\",\"3\":\"38.5\",\"4\":\"17.9\",\"5\":\"190\",\"6\":\"3325\",\"7\":\"female\",\"8\":\"2009\"},{\"1\":\"Adelie\",\"2\":\"Torgersen\",\"3\":\"43.1\",\"4\":\"19.2\",\"5\":\"197\",\"6\":\"3500\",\"7\":\"male\",\"8\":\"2009\"},{\"1\":\"Adelie\",\"2\":\"Dream\",\"3\":\"36.8\",\"4\":\"18.5\",\"5\":\"193\",\"6\":\"3500\",\"7\":\"female\",\"8\":\"2009\"},{\"1\":\"Adelie\",\"2\":\"Dream\",\"3\":\"37.5\",\"4\":\"18.5\",\"5\":\"199\",\"6\":\"4475\",\"7\":\"male\",\"8\":\"2009\"},{\"1\":\"Adelie\",\"2\":\"Dream\",\"3\":\"38.1\",\"4\":\"17.6\",\"5\":\"187\",\"6\":\"3425\",\"7\":\"female\",\"8\":\"2009\"},{\"1\":\"Adelie\",\"2\":\"Dream\",\"3\":\"41.1\",\"4\":\"17.5\",\"5\":\"190\",\"6\":\"3900\",\"7\":\"male\",\"8\":\"2009\"},{\"1\":\"Adelie\",\"2\":\"Dream\",\"3\":\"35.6\",\"4\":\"17.5\",\"5\":\"191\",\"6\":\"3175\",\"7\":\"female\",\"8\":\"2009\"},{\"1\":\"Adelie\",\"2\":\"Dream\",\"3\":\"40.2\",\"4\":\"20.1\",\"5\":\"200\",\"6\":\"3975\",\"7\":\"male\",\"8\":\"2009\"},{\"1\":\"Adelie\",\"2\":\"Dream\",\"3\":\"37.0\",\"4\":\"16.5\",\"5\":\"185\",\"6\":\"3400\",\"7\":\"female\",\"8\":\"2009\"},{\"1\":\"Adelie\",\"2\":\"Dream\",\"3\":\"39.7\",\"4\":\"17.9\",\"5\":\"193\",\"6\":\"4250\",\"7\":\"male\",\"8\":\"2009\"},{\"1\":\"Adelie\",\"2\":\"Dream\",\"3\":\"40.2\",\"4\":\"17.1\",\"5\":\"193\",\"6\":\"3400\",\"7\":\"female\",\"8\":\"2009\"},{\"1\":\"Adelie\",\"2\":\"Dream\",\"3\":\"40.6\",\"4\":\"17.2\",\"5\":\"187\",\"6\":\"3475\",\"7\":\"male\",\"8\":\"2009\"},{\"1\":\"Adelie\",\"2\":\"Dream\",\"3\":\"32.1\",\"4\":\"15.5\",\"5\":\"188\",\"6\":\"3050\",\"7\":\"female\",\"8\":\"2009\"},{\"1\":\"Adelie\",\"2\":\"Dream\",\"3\":\"40.7\",\"4\":\"17.0\",\"5\":\"190\",\"6\":\"3725\",\"7\":\"male\",\"8\":\"2009\"},{\"1\":\"Adelie\",\"2\":\"Dream\",\"3\":\"37.3\",\"4\":\"16.8\",\"5\":\"192\",\"6\":\"3000\",\"7\":\"female\",\"8\":\"2009\"},{\"1\":\"Adelie\",\"2\":\"Dream\",\"3\":\"39.0\",\"4\":\"18.7\",\"5\":\"185\",\"6\":\"3650\",\"7\":\"male\",\"8\":\"2009\"},{\"1\":\"Adelie\",\"2\":\"Dream\",\"3\":\"39.2\",\"4\":\"18.6\",\"5\":\"190\",\"6\":\"4250\",\"7\":\"male\",\"8\":\"2009\"},{\"1\":\"Adelie\",\"2\":\"Dream\",\"3\":\"36.6\",\"4\":\"18.4\",\"5\":\"184\",\"6\":\"3475\",\"7\":\"female\",\"8\":\"2009\"},{\"1\":\"Adelie\",\"2\":\"Dream\",\"3\":\"36.0\",\"4\":\"17.8\",\"5\":\"195\",\"6\":\"3450\",\"7\":\"female\",\"8\":\"2009\"},{\"1\":\"Adelie\",\"2\":\"Dream\",\"3\":\"37.8\",\"4\":\"18.1\",\"5\":\"193\",\"6\":\"3750\",\"7\":\"male\",\"8\":\"2009\"},{\"1\":\"Adelie\",\"2\":\"Dream\",\"3\":\"36.0\",\"4\":\"17.1\",\"5\":\"187\",\"6\":\"3700\",\"7\":\"female\",\"8\":\"2009\"},{\"1\":\"Adelie\",\"2\":\"Dream\",\"3\":\"41.5\",\"4\":\"18.5\",\"5\":\"201\",\"6\":\"4000\",\"7\":\"male\",\"8\":\"2009\"},{\"1\":\"Gentoo\",\"2\":\"Biscoe\",\"3\":\"46.1\",\"4\":\"13.2\",\"5\":\"211\",\"6\":\"4500\",\"7\":\"female\",\"8\":\"2007\"},{\"1\":\"Gentoo\",\"2\":\"Biscoe\",\"3\":\"50.0\",\"4\":\"16.3\",\"5\":\"230\",\"6\":\"5700\",\"7\":\"male\",\"8\":\"2007\"},{\"1\":\"Gentoo\",\"2\":\"Biscoe\",\"3\":\"48.7\",\"4\":\"14.1\",\"5\":\"210\",\"6\":\"4450\",\"7\":\"female\",\"8\":\"2007\"},{\"1\":\"Gentoo\",\"2\":\"Biscoe\",\"3\":\"50.0\",\"4\":\"15.2\",\"5\":\"218\",\"6\":\"5700\",\"7\":\"male\",\"8\":\"2007\"},{\"1\":\"Gentoo\",\"2\":\"Biscoe\",\"3\":\"47.6\",\"4\":\"14.5\",\"5\":\"215\",\"6\":\"5400\",\"7\":\"male\",\"8\":\"2007\"},{\"1\":\"Gentoo\",\"2\":\"Biscoe\",\"3\":\"46.5\",\"4\":\"13.5\",\"5\":\"210\",\"6\":\"4550\",\"7\":\"female\",\"8\":\"2007\"},{\"1\":\"Gentoo\",\"2\":\"Biscoe\",\"3\":\"45.4\",\"4\":\"14.6\",\"5\":\"211\",\"6\":\"4800\",\"7\":\"female\",\"8\":\"2007\"},{\"1\":\"Gentoo\",\"2\":\"Biscoe\",\"3\":\"46.7\",\"4\":\"15.3\",\"5\":\"219\",\"6\":\"5200\",\"7\":\"male\",\"8\":\"2007\"},{\"1\":\"Gentoo\",\"2\":\"Biscoe\",\"3\":\"43.3\",\"4\":\"13.4\",\"5\":\"209\",\"6\":\"4400\",\"7\":\"female\",\"8\":\"2007\"},{\"1\":\"Gentoo\",\"2\":\"Biscoe\",\"3\":\"46.8\",\"4\":\"15.4\",\"5\":\"215\",\"6\":\"5150\",\"7\":\"male\",\"8\":\"2007\"},{\"1\":\"Gentoo\",\"2\":\"Biscoe\",\"3\":\"40.9\",\"4\":\"13.7\",\"5\":\"214\",\"6\":\"4650\",\"7\":\"female\",\"8\":\"2007\"},{\"1\":\"Gentoo\",\"2\":\"Biscoe\",\"3\":\"49.0\",\"4\":\"16.1\",\"5\":\"216\",\"6\":\"5550\",\"7\":\"male\",\"8\":\"2007\"},{\"1\":\"Gentoo\",\"2\":\"Biscoe\",\"3\":\"45.5\",\"4\":\"13.7\",\"5\":\"214\",\"6\":\"4650\",\"7\":\"female\",\"8\":\"2007\"},{\"1\":\"Gentoo\",\"2\":\"Biscoe\",\"3\":\"48.4\",\"4\":\"14.6\",\"5\":\"213\",\"6\":\"5850\",\"7\":\"male\",\"8\":\"2007\"},{\"1\":\"Gentoo\",\"2\":\"Biscoe\",\"3\":\"45.8\",\"4\":\"14.6\",\"5\":\"210\",\"6\":\"4200\",\"7\":\"female\",\"8\":\"2007\"},{\"1\":\"Gentoo\",\"2\":\"Biscoe\",\"3\":\"49.3\",\"4\":\"15.7\",\"5\":\"217\",\"6\":\"5850\",\"7\":\"male\",\"8\":\"2007\"},{\"1\":\"Gentoo\",\"2\":\"Biscoe\",\"3\":\"42.0\",\"4\":\"13.5\",\"5\":\"210\",\"6\":\"4150\",\"7\":\"female\",\"8\":\"2007\"},{\"1\":\"Gentoo\",\"2\":\"Biscoe\",\"3\":\"49.2\",\"4\":\"15.2\",\"5\":\"221\",\"6\":\"6300\",\"7\":\"male\",\"8\":\"2007\"},{\"1\":\"Gentoo\",\"2\":\"Biscoe\",\"3\":\"46.2\",\"4\":\"14.5\",\"5\":\"209\",\"6\":\"4800\",\"7\":\"female\",\"8\":\"2007\"},{\"1\":\"Gentoo\",\"2\":\"Biscoe\",\"3\":\"48.7\",\"4\":\"15.1\",\"5\":\"222\",\"6\":\"5350\",\"7\":\"male\",\"8\":\"2007\"},{\"1\":\"Gentoo\",\"2\":\"Biscoe\",\"3\":\"50.2\",\"4\":\"14.3\",\"5\":\"218\",\"6\":\"5700\",\"7\":\"male\",\"8\":\"2007\"},{\"1\":\"Gentoo\",\"2\":\"Biscoe\",\"3\":\"45.1\",\"4\":\"14.5\",\"5\":\"215\",\"6\":\"5000\",\"7\":\"female\",\"8\":\"2007\"},{\"1\":\"Gentoo\",\"2\":\"Biscoe\",\"3\":\"46.5\",\"4\":\"14.5\",\"5\":\"213\",\"6\":\"4400\",\"7\":\"female\",\"8\":\"2007\"},{\"1\":\"Gentoo\",\"2\":\"Biscoe\",\"3\":\"46.3\",\"4\":\"15.8\",\"5\":\"215\",\"6\":\"5050\",\"7\":\"male\",\"8\":\"2007\"},{\"1\":\"Gentoo\",\"2\":\"Biscoe\",\"3\":\"42.9\",\"4\":\"13.1\",\"5\":\"215\",\"6\":\"5000\",\"7\":\"female\",\"8\":\"2007\"},{\"1\":\"Gentoo\",\"2\":\"Biscoe\",\"3\":\"46.1\",\"4\":\"15.1\",\"5\":\"215\",\"6\":\"5100\",\"7\":\"male\",\"8\":\"2007\"},{\"1\":\"Gentoo\",\"2\":\"Biscoe\",\"3\":\"47.8\",\"4\":\"15.0\",\"5\":\"215\",\"6\":\"5650\",\"7\":\"male\",\"8\":\"2007\"},{\"1\":\"Gentoo\",\"2\":\"Biscoe\",\"3\":\"48.2\",\"4\":\"14.3\",\"5\":\"210\",\"6\":\"4600\",\"7\":\"female\",\"8\":\"2007\"},{\"1\":\"Gentoo\",\"2\":\"Biscoe\",\"3\":\"50.0\",\"4\":\"15.3\",\"5\":\"220\",\"6\":\"5550\",\"7\":\"male\",\"8\":\"2007\"},{\"1\":\"Gentoo\",\"2\":\"Biscoe\",\"3\":\"47.3\",\"4\":\"15.3\",\"5\":\"222\",\"6\":\"5250\",\"7\":\"male\",\"8\":\"2007\"},{\"1\":\"Gentoo\",\"2\":\"Biscoe\",\"3\":\"42.8\",\"4\":\"14.2\",\"5\":\"209\",\"6\":\"4700\",\"7\":\"female\",\"8\":\"2007\"},{\"1\":\"Gentoo\",\"2\":\"Biscoe\",\"3\":\"45.1\",\"4\":\"14.5\",\"5\":\"207\",\"6\":\"5050\",\"7\":\"female\",\"8\":\"2007\"},{\"1\":\"Gentoo\",\"2\":\"Biscoe\",\"3\":\"59.6\",\"4\":\"17.0\",\"5\":\"230\",\"6\":\"6050\",\"7\":\"male\",\"8\":\"2007\"},{\"1\":\"Gentoo\",\"2\":\"Biscoe\",\"3\":\"49.1\",\"4\":\"14.8\",\"5\":\"220\",\"6\":\"5150\",\"7\":\"female\",\"8\":\"2008\"},{\"1\":\"Gentoo\",\"2\":\"Biscoe\",\"3\":\"48.4\",\"4\":\"16.3\",\"5\":\"220\",\"6\":\"5400\",\"7\":\"male\",\"8\":\"2008\"},{\"1\":\"Gentoo\",\"2\":\"Biscoe\",\"3\":\"42.6\",\"4\":\"13.7\",\"5\":\"213\",\"6\":\"4950\",\"7\":\"female\",\"8\":\"2008\"},{\"1\":\"Gentoo\",\"2\":\"Biscoe\",\"3\":\"44.4\",\"4\":\"17.3\",\"5\":\"219\",\"6\":\"5250\",\"7\":\"male\",\"8\":\"2008\"},{\"1\":\"Gentoo\",\"2\":\"Biscoe\",\"3\":\"44.0\",\"4\":\"13.6\",\"5\":\"208\",\"6\":\"4350\",\"7\":\"female\",\"8\":\"2008\"},{\"1\":\"Gentoo\",\"2\":\"Biscoe\",\"3\":\"48.7\",\"4\":\"15.7\",\"5\":\"208\",\"6\":\"5350\",\"7\":\"male\",\"8\":\"2008\"},{\"1\":\"Gentoo\",\"2\":\"Biscoe\",\"3\":\"42.7\",\"4\":\"13.7\",\"5\":\"208\",\"6\":\"3950\",\"7\":\"female\",\"8\":\"2008\"},{\"1\":\"Gentoo\",\"2\":\"Biscoe\",\"3\":\"49.6\",\"4\":\"16.0\",\"5\":\"225\",\"6\":\"5700\",\"7\":\"male\",\"8\":\"2008\"},{\"1\":\"Gentoo\",\"2\":\"Biscoe\",\"3\":\"45.3\",\"4\":\"13.7\",\"5\":\"210\",\"6\":\"4300\",\"7\":\"female\",\"8\":\"2008\"},{\"1\":\"Gentoo\",\"2\":\"Biscoe\",\"3\":\"49.6\",\"4\":\"15.0\",\"5\":\"216\",\"6\":\"4750\",\"7\":\"male\",\"8\":\"2008\"},{\"1\":\"Gentoo\",\"2\":\"Biscoe\",\"3\":\"50.5\",\"4\":\"15.9\",\"5\":\"222\",\"6\":\"5550\",\"7\":\"male\",\"8\":\"2008\"},{\"1\":\"Gentoo\",\"2\":\"Biscoe\",\"3\":\"43.6\",\"4\":\"13.9\",\"5\":\"217\",\"6\":\"4900\",\"7\":\"female\",\"8\":\"2008\"},{\"1\":\"Gentoo\",\"2\":\"Biscoe\",\"3\":\"45.5\",\"4\":\"13.9\",\"5\":\"210\",\"6\":\"4200\",\"7\":\"female\",\"8\":\"2008\"},{\"1\":\"Gentoo\",\"2\":\"Biscoe\",\"3\":\"50.5\",\"4\":\"15.9\",\"5\":\"225\",\"6\":\"5400\",\"7\":\"male\",\"8\":\"2008\"},{\"1\":\"Gentoo\",\"2\":\"Biscoe\",\"3\":\"44.9\",\"4\":\"13.3\",\"5\":\"213\",\"6\":\"5100\",\"7\":\"female\",\"8\":\"2008\"},{\"1\":\"Gentoo\",\"2\":\"Biscoe\",\"3\":\"45.2\",\"4\":\"15.8\",\"5\":\"215\",\"6\":\"5300\",\"7\":\"male\",\"8\":\"2008\"},{\"1\":\"Gentoo\",\"2\":\"Biscoe\",\"3\":\"46.6\",\"4\":\"14.2\",\"5\":\"210\",\"6\":\"4850\",\"7\":\"female\",\"8\":\"2008\"},{\"1\":\"Gentoo\",\"2\":\"Biscoe\",\"3\":\"48.5\",\"4\":\"14.1\",\"5\":\"220\",\"6\":\"5300\",\"7\":\"male\",\"8\":\"2008\"},{\"1\":\"Gentoo\",\"2\":\"Biscoe\",\"3\":\"45.1\",\"4\":\"14.4\",\"5\":\"210\",\"6\":\"4400\",\"7\":\"female\",\"8\":\"2008\"},{\"1\":\"Gentoo\",\"2\":\"Biscoe\",\"3\":\"50.1\",\"4\":\"15.0\",\"5\":\"225\",\"6\":\"5000\",\"7\":\"male\",\"8\":\"2008\"},{\"1\":\"Gentoo\",\"2\":\"Biscoe\",\"3\":\"46.5\",\"4\":\"14.4\",\"5\":\"217\",\"6\":\"4900\",\"7\":\"female\",\"8\":\"2008\"},{\"1\":\"Gentoo\",\"2\":\"Biscoe\",\"3\":\"45.0\",\"4\":\"15.4\",\"5\":\"220\",\"6\":\"5050\",\"7\":\"male\",\"8\":\"2008\"},{\"1\":\"Gentoo\",\"2\":\"Biscoe\",\"3\":\"43.8\",\"4\":\"13.9\",\"5\":\"208\",\"6\":\"4300\",\"7\":\"female\",\"8\":\"2008\"},{\"1\":\"Gentoo\",\"2\":\"Biscoe\",\"3\":\"45.5\",\"4\":\"15.0\",\"5\":\"220\",\"6\":\"5000\",\"7\":\"male\",\"8\":\"2008\"},{\"1\":\"Gentoo\",\"2\":\"Biscoe\",\"3\":\"43.2\",\"4\":\"14.5\",\"5\":\"208\",\"6\":\"4450\",\"7\":\"female\",\"8\":\"2008\"},{\"1\":\"Gentoo\",\"2\":\"Biscoe\",\"3\":\"50.4\",\"4\":\"15.3\",\"5\":\"224\",\"6\":\"5550\",\"7\":\"male\",\"8\":\"2008\"},{\"1\":\"Gentoo\",\"2\":\"Biscoe\",\"3\":\"45.3\",\"4\":\"13.8\",\"5\":\"208\",\"6\":\"4200\",\"7\":\"female\",\"8\":\"2008\"},{\"1\":\"Gentoo\",\"2\":\"Biscoe\",\"3\":\"46.2\",\"4\":\"14.9\",\"5\":\"221\",\"6\":\"5300\",\"7\":\"male\",\"8\":\"2008\"},{\"1\":\"Gentoo\",\"2\":\"Biscoe\",\"3\":\"45.7\",\"4\":\"13.9\",\"5\":\"214\",\"6\":\"4400\",\"7\":\"female\",\"8\":\"2008\"},{\"1\":\"Gentoo\",\"2\":\"Biscoe\",\"3\":\"54.3\",\"4\":\"15.7\",\"5\":\"231\",\"6\":\"5650\",\"7\":\"male\",\"8\":\"2008\"},{\"1\":\"Gentoo\",\"2\":\"Biscoe\",\"3\":\"45.8\",\"4\":\"14.2\",\"5\":\"219\",\"6\":\"4700\",\"7\":\"female\",\"8\":\"2008\"},{\"1\":\"Gentoo\",\"2\":\"Biscoe\",\"3\":\"49.8\",\"4\":\"16.8\",\"5\":\"230\",\"6\":\"5700\",\"7\":\"male\",\"8\":\"2008\"},{\"1\":\"Gentoo\",\"2\":\"Biscoe\",\"3\":\"49.5\",\"4\":\"16.2\",\"5\":\"229\",\"6\":\"5800\",\"7\":\"male\",\"8\":\"2008\"},{\"1\":\"Gentoo\",\"2\":\"Biscoe\",\"3\":\"43.5\",\"4\":\"14.2\",\"5\":\"220\",\"6\":\"4700\",\"7\":\"female\",\"8\":\"2008\"},{\"1\":\"Gentoo\",\"2\":\"Biscoe\",\"3\":\"50.7\",\"4\":\"15.0\",\"5\":\"223\",\"6\":\"5550\",\"7\":\"male\",\"8\":\"2008\"},{\"1\":\"Gentoo\",\"2\":\"Biscoe\",\"3\":\"47.7\",\"4\":\"15.0\",\"5\":\"216\",\"6\":\"4750\",\"7\":\"female\",\"8\":\"2008\"},{\"1\":\"Gentoo\",\"2\":\"Biscoe\",\"3\":\"46.4\",\"4\":\"15.6\",\"5\":\"221\",\"6\":\"5000\",\"7\":\"male\",\"8\":\"2008\"},{\"1\":\"Gentoo\",\"2\":\"Biscoe\",\"3\":\"48.2\",\"4\":\"15.6\",\"5\":\"221\",\"6\":\"5100\",\"7\":\"male\",\"8\":\"2008\"},{\"1\":\"Gentoo\",\"2\":\"Biscoe\",\"3\":\"46.5\",\"4\":\"14.8\",\"5\":\"217\",\"6\":\"5200\",\"7\":\"female\",\"8\":\"2008\"},{\"1\":\"Gentoo\",\"2\":\"Biscoe\",\"3\":\"46.4\",\"4\":\"15.0\",\"5\":\"216\",\"6\":\"4700\",\"7\":\"female\",\"8\":\"2008\"},{\"1\":\"Gentoo\",\"2\":\"Biscoe\",\"3\":\"48.6\",\"4\":\"16.0\",\"5\":\"230\",\"6\":\"5800\",\"7\":\"male\",\"8\":\"2008\"},{\"1\":\"Gentoo\",\"2\":\"Biscoe\",\"3\":\"47.5\",\"4\":\"14.2\",\"5\":\"209\",\"6\":\"4600\",\"7\":\"female\",\"8\":\"2008\"},{\"1\":\"Gentoo\",\"2\":\"Biscoe\",\"3\":\"51.1\",\"4\":\"16.3\",\"5\":\"220\",\"6\":\"6000\",\"7\":\"male\",\"8\":\"2008\"},{\"1\":\"Gentoo\",\"2\":\"Biscoe\",\"3\":\"45.2\",\"4\":\"13.8\",\"5\":\"215\",\"6\":\"4750\",\"7\":\"female\",\"8\":\"2008\"},{\"1\":\"Gentoo\",\"2\":\"Biscoe\",\"3\":\"45.2\",\"4\":\"16.4\",\"5\":\"223\",\"6\":\"5950\",\"7\":\"male\",\"8\":\"2008\"},{\"1\":\"Gentoo\",\"2\":\"Biscoe\",\"3\":\"49.1\",\"4\":\"14.5\",\"5\":\"212\",\"6\":\"4625\",\"7\":\"female\",\"8\":\"2009\"},{\"1\":\"Gentoo\",\"2\":\"Biscoe\",\"3\":\"52.5\",\"4\":\"15.6\",\"5\":\"221\",\"6\":\"5450\",\"7\":\"male\",\"8\":\"2009\"},{\"1\":\"Gentoo\",\"2\":\"Biscoe\",\"3\":\"47.4\",\"4\":\"14.6\",\"5\":\"212\",\"6\":\"4725\",\"7\":\"female\",\"8\":\"2009\"},{\"1\":\"Gentoo\",\"2\":\"Biscoe\",\"3\":\"50.0\",\"4\":\"15.9\",\"5\":\"224\",\"6\":\"5350\",\"7\":\"male\",\"8\":\"2009\"},{\"1\":\"Gentoo\",\"2\":\"Biscoe\",\"3\":\"44.9\",\"4\":\"13.8\",\"5\":\"212\",\"6\":\"4750\",\"7\":\"female\",\"8\":\"2009\"},{\"1\":\"Gentoo\",\"2\":\"Biscoe\",\"3\":\"50.8\",\"4\":\"17.3\",\"5\":\"228\",\"6\":\"5600\",\"7\":\"male\",\"8\":\"2009\"},{\"1\":\"Gentoo\",\"2\":\"Biscoe\",\"3\":\"43.4\",\"4\":\"14.4\",\"5\":\"218\",\"6\":\"4600\",\"7\":\"female\",\"8\":\"2009\"},{\"1\":\"Gentoo\",\"2\":\"Biscoe\",\"3\":\"51.3\",\"4\":\"14.2\",\"5\":\"218\",\"6\":\"5300\",\"7\":\"male\",\"8\":\"2009\"},{\"1\":\"Gentoo\",\"2\":\"Biscoe\",\"3\":\"47.5\",\"4\":\"14.0\",\"5\":\"212\",\"6\":\"4875\",\"7\":\"female\",\"8\":\"2009\"},{\"1\":\"Gentoo\",\"2\":\"Biscoe\",\"3\":\"52.1\",\"4\":\"17.0\",\"5\":\"230\",\"6\":\"5550\",\"7\":\"male\",\"8\":\"2009\"},{\"1\":\"Gentoo\",\"2\":\"Biscoe\",\"3\":\"47.5\",\"4\":\"15.0\",\"5\":\"218\",\"6\":\"4950\",\"7\":\"female\",\"8\":\"2009\"},{\"1\":\"Gentoo\",\"2\":\"Biscoe\",\"3\":\"52.2\",\"4\":\"17.1\",\"5\":\"228\",\"6\":\"5400\",\"7\":\"male\",\"8\":\"2009\"},{\"1\":\"Gentoo\",\"2\":\"Biscoe\",\"3\":\"45.5\",\"4\":\"14.5\",\"5\":\"212\",\"6\":\"4750\",\"7\":\"female\",\"8\":\"2009\"},{\"1\":\"Gentoo\",\"2\":\"Biscoe\",\"3\":\"49.5\",\"4\":\"16.1\",\"5\":\"224\",\"6\":\"5650\",\"7\":\"male\",\"8\":\"2009\"},{\"1\":\"Gentoo\",\"2\":\"Biscoe\",\"3\":\"44.5\",\"4\":\"14.7\",\"5\":\"214\",\"6\":\"4850\",\"7\":\"female\",\"8\":\"2009\"},{\"1\":\"Gentoo\",\"2\":\"Biscoe\",\"3\":\"50.8\",\"4\":\"15.7\",\"5\":\"226\",\"6\":\"5200\",\"7\":\"male\",\"8\":\"2009\"},{\"1\":\"Gentoo\",\"2\":\"Biscoe\",\"3\":\"49.4\",\"4\":\"15.8\",\"5\":\"216\",\"6\":\"4925\",\"7\":\"male\",\"8\":\"2009\"},{\"1\":\"Gentoo\",\"2\":\"Biscoe\",\"3\":\"46.9\",\"4\":\"14.6\",\"5\":\"222\",\"6\":\"4875\",\"7\":\"female\",\"8\":\"2009\"},{\"1\":\"Gentoo\",\"2\":\"Biscoe\",\"3\":\"48.4\",\"4\":\"14.4\",\"5\":\"203\",\"6\":\"4625\",\"7\":\"female\",\"8\":\"2009\"},{\"1\":\"Gentoo\",\"2\":\"Biscoe\",\"3\":\"51.1\",\"4\":\"16.5\",\"5\":\"225\",\"6\":\"5250\",\"7\":\"male\",\"8\":\"2009\"},{\"1\":\"Gentoo\",\"2\":\"Biscoe\",\"3\":\"48.5\",\"4\":\"15.0\",\"5\":\"219\",\"6\":\"4850\",\"7\":\"female\",\"8\":\"2009\"},{\"1\":\"Gentoo\",\"2\":\"Biscoe\",\"3\":\"55.9\",\"4\":\"17.0\",\"5\":\"228\",\"6\":\"5600\",\"7\":\"male\",\"8\":\"2009\"},{\"1\":\"Gentoo\",\"2\":\"Biscoe\",\"3\":\"47.2\",\"4\":\"15.5\",\"5\":\"215\",\"6\":\"4975\",\"7\":\"female\",\"8\":\"2009\"},{\"1\":\"Gentoo\",\"2\":\"Biscoe\",\"3\":\"49.1\",\"4\":\"15.0\",\"5\":\"228\",\"6\":\"5500\",\"7\":\"male\",\"8\":\"2009\"},{\"1\":\"Gentoo\",\"2\":\"Biscoe\",\"3\":\"46.8\",\"4\":\"16.1\",\"5\":\"215\",\"6\":\"5500\",\"7\":\"male\",\"8\":\"2009\"},{\"1\":\"Gentoo\",\"2\":\"Biscoe\",\"3\":\"41.7\",\"4\":\"14.7\",\"5\":\"210\",\"6\":\"4700\",\"7\":\"female\",\"8\":\"2009\"},{\"1\":\"Gentoo\",\"2\":\"Biscoe\",\"3\":\"53.4\",\"4\":\"15.8\",\"5\":\"219\",\"6\":\"5500\",\"7\":\"male\",\"8\":\"2009\"},{\"1\":\"Gentoo\",\"2\":\"Biscoe\",\"3\":\"43.3\",\"4\":\"14.0\",\"5\":\"208\",\"6\":\"4575\",\"7\":\"female\",\"8\":\"2009\"},{\"1\":\"Gentoo\",\"2\":\"Biscoe\",\"3\":\"48.1\",\"4\":\"15.1\",\"5\":\"209\",\"6\":\"5500\",\"7\":\"male\",\"8\":\"2009\"},{\"1\":\"Gentoo\",\"2\":\"Biscoe\",\"3\":\"50.5\",\"4\":\"15.2\",\"5\":\"216\",\"6\":\"5000\",\"7\":\"female\",\"8\":\"2009\"},{\"1\":\"Gentoo\",\"2\":\"Biscoe\",\"3\":\"49.8\",\"4\":\"15.9\",\"5\":\"229\",\"6\":\"5950\",\"7\":\"male\",\"8\":\"2009\"},{\"1\":\"Gentoo\",\"2\":\"Biscoe\",\"3\":\"43.5\",\"4\":\"15.2\",\"5\":\"213\",\"6\":\"4650\",\"7\":\"female\",\"8\":\"2009\"},{\"1\":\"Gentoo\",\"2\":\"Biscoe\",\"3\":\"51.5\",\"4\":\"16.3\",\"5\":\"230\",\"6\":\"5500\",\"7\":\"male\",\"8\":\"2009\"},{\"1\":\"Gentoo\",\"2\":\"Biscoe\",\"3\":\"46.2\",\"4\":\"14.1\",\"5\":\"217\",\"6\":\"4375\",\"7\":\"female\",\"8\":\"2009\"},{\"1\":\"Gentoo\",\"2\":\"Biscoe\",\"3\":\"55.1\",\"4\":\"16.0\",\"5\":\"230\",\"6\":\"5850\",\"7\":\"male\",\"8\":\"2009\"},{\"1\":\"Gentoo\",\"2\":\"Biscoe\",\"3\":\"48.8\",\"4\":\"16.2\",\"5\":\"222\",\"6\":\"6000\",\"7\":\"male\",\"8\":\"2009\"},{\"1\":\"Gentoo\",\"2\":\"Biscoe\",\"3\":\"47.2\",\"4\":\"13.7\",\"5\":\"214\",\"6\":\"4925\",\"7\":\"female\",\"8\":\"2009\"},{\"1\":\"Gentoo\",\"2\":\"Biscoe\",\"3\":\"46.8\",\"4\":\"14.3\",\"5\":\"215\",\"6\":\"4850\",\"7\":\"female\",\"8\":\"2009\"},{\"1\":\"Gentoo\",\"2\":\"Biscoe\",\"3\":\"50.4\",\"4\":\"15.7\",\"5\":\"222\",\"6\":\"5750\",\"7\":\"male\",\"8\":\"2009\"},{\"1\":\"Gentoo\",\"2\":\"Biscoe\",\"3\":\"45.2\",\"4\":\"14.8\",\"5\":\"212\",\"6\":\"5200\",\"7\":\"female\",\"8\":\"2009\"},{\"1\":\"Gentoo\",\"2\":\"Biscoe\",\"3\":\"49.9\",\"4\":\"16.1\",\"5\":\"213\",\"6\":\"5400\",\"7\":\"male\",\"8\":\"2009\"},{\"1\":\"Chinstrap\",\"2\":\"Dream\",\"3\":\"46.5\",\"4\":\"17.9\",\"5\":\"192\",\"6\":\"3500\",\"7\":\"female\",\"8\":\"2007\"},{\"1\":\"Chinstrap\",\"2\":\"Dream\",\"3\":\"50.0\",\"4\":\"19.5\",\"5\":\"196\",\"6\":\"3900\",\"7\":\"male\",\"8\":\"2007\"},{\"1\":\"Chinstrap\",\"2\":\"Dream\",\"3\":\"51.3\",\"4\":\"19.2\",\"5\":\"193\",\"6\":\"3650\",\"7\":\"male\",\"8\":\"2007\"},{\"1\":\"Chinstrap\",\"2\":\"Dream\",\"3\":\"45.4\",\"4\":\"18.7\",\"5\":\"188\",\"6\":\"3525\",\"7\":\"female\",\"8\":\"2007\"},{\"1\":\"Chinstrap\",\"2\":\"Dream\",\"3\":\"52.7\",\"4\":\"19.8\",\"5\":\"197\",\"6\":\"3725\",\"7\":\"male\",\"8\":\"2007\"},{\"1\":\"Chinstrap\",\"2\":\"Dream\",\"3\":\"45.2\",\"4\":\"17.8\",\"5\":\"198\",\"6\":\"3950\",\"7\":\"female\",\"8\":\"2007\"},{\"1\":\"Chinstrap\",\"2\":\"Dream\",\"3\":\"46.1\",\"4\":\"18.2\",\"5\":\"178\",\"6\":\"3250\",\"7\":\"female\",\"8\":\"2007\"},{\"1\":\"Chinstrap\",\"2\":\"Dream\",\"3\":\"51.3\",\"4\":\"18.2\",\"5\":\"197\",\"6\":\"3750\",\"7\":\"male\",\"8\":\"2007\"},{\"1\":\"Chinstrap\",\"2\":\"Dream\",\"3\":\"46.0\",\"4\":\"18.9\",\"5\":\"195\",\"6\":\"4150\",\"7\":\"female\",\"8\":\"2007\"},{\"1\":\"Chinstrap\",\"2\":\"Dream\",\"3\":\"51.3\",\"4\":\"19.9\",\"5\":\"198\",\"6\":\"3700\",\"7\":\"male\",\"8\":\"2007\"},{\"1\":\"Chinstrap\",\"2\":\"Dream\",\"3\":\"46.6\",\"4\":\"17.8\",\"5\":\"193\",\"6\":\"3800\",\"7\":\"female\",\"8\":\"2007\"},{\"1\":\"Chinstrap\",\"2\":\"Dream\",\"3\":\"51.7\",\"4\":\"20.3\",\"5\":\"194\",\"6\":\"3775\",\"7\":\"male\",\"8\":\"2007\"},{\"1\":\"Chinstrap\",\"2\":\"Dream\",\"3\":\"47.0\",\"4\":\"17.3\",\"5\":\"185\",\"6\":\"3700\",\"7\":\"female\",\"8\":\"2007\"},{\"1\":\"Chinstrap\",\"2\":\"Dream\",\"3\":\"52.0\",\"4\":\"18.1\",\"5\":\"201\",\"6\":\"4050\",\"7\":\"male\",\"8\":\"2007\"},{\"1\":\"Chinstrap\",\"2\":\"Dream\",\"3\":\"45.9\",\"4\":\"17.1\",\"5\":\"190\",\"6\":\"3575\",\"7\":\"female\",\"8\":\"2007\"},{\"1\":\"Chinstrap\",\"2\":\"Dream\",\"3\":\"50.5\",\"4\":\"19.6\",\"5\":\"201\",\"6\":\"4050\",\"7\":\"male\",\"8\":\"2007\"},{\"1\":\"Chinstrap\",\"2\":\"Dream\",\"3\":\"50.3\",\"4\":\"20.0\",\"5\":\"197\",\"6\":\"3300\",\"7\":\"male\",\"8\":\"2007\"},{\"1\":\"Chinstrap\",\"2\":\"Dream\",\"3\":\"58.0\",\"4\":\"17.8\",\"5\":\"181\",\"6\":\"3700\",\"7\":\"female\",\"8\":\"2007\"},{\"1\":\"Chinstrap\",\"2\":\"Dream\",\"3\":\"46.4\",\"4\":\"18.6\",\"5\":\"190\",\"6\":\"3450\",\"7\":\"female\",\"8\":\"2007\"},{\"1\":\"Chinstrap\",\"2\":\"Dream\",\"3\":\"49.2\",\"4\":\"18.2\",\"5\":\"195\",\"6\":\"4400\",\"7\":\"male\",\"8\":\"2007\"},{\"1\":\"Chinstrap\",\"2\":\"Dream\",\"3\":\"42.4\",\"4\":\"17.3\",\"5\":\"181\",\"6\":\"3600\",\"7\":\"female\",\"8\":\"2007\"},{\"1\":\"Chinstrap\",\"2\":\"Dream\",\"3\":\"48.5\",\"4\":\"17.5\",\"5\":\"191\",\"6\":\"3400\",\"7\":\"male\",\"8\":\"2007\"},{\"1\":\"Chinstrap\",\"2\":\"Dream\",\"3\":\"43.2\",\"4\":\"16.6\",\"5\":\"187\",\"6\":\"2900\",\"7\":\"female\",\"8\":\"2007\"},{\"1\":\"Chinstrap\",\"2\":\"Dream\",\"3\":\"50.6\",\"4\":\"19.4\",\"5\":\"193\",\"6\":\"3800\",\"7\":\"male\",\"8\":\"2007\"},{\"1\":\"Chinstrap\",\"2\":\"Dream\",\"3\":\"46.7\",\"4\":\"17.9\",\"5\":\"195\",\"6\":\"3300\",\"7\":\"female\",\"8\":\"2007\"},{\"1\":\"Chinstrap\",\"2\":\"Dream\",\"3\":\"52.0\",\"4\":\"19.0\",\"5\":\"197\",\"6\":\"4150\",\"7\":\"male\",\"8\":\"2007\"},{\"1\":\"Chinstrap\",\"2\":\"Dream\",\"3\":\"50.5\",\"4\":\"18.4\",\"5\":\"200\",\"6\":\"3400\",\"7\":\"female\",\"8\":\"2008\"},{\"1\":\"Chinstrap\",\"2\":\"Dream\",\"3\":\"49.5\",\"4\":\"19.0\",\"5\":\"200\",\"6\":\"3800\",\"7\":\"male\",\"8\":\"2008\"},{\"1\":\"Chinstrap\",\"2\":\"Dream\",\"3\":\"46.4\",\"4\":\"17.8\",\"5\":\"191\",\"6\":\"3700\",\"7\":\"female\",\"8\":\"2008\"},{\"1\":\"Chinstrap\",\"2\":\"Dream\",\"3\":\"52.8\",\"4\":\"20.0\",\"5\":\"205\",\"6\":\"4550\",\"7\":\"male\",\"8\":\"2008\"},{\"1\":\"Chinstrap\",\"2\":\"Dream\",\"3\":\"40.9\",\"4\":\"16.6\",\"5\":\"187\",\"6\":\"3200\",\"7\":\"female\",\"8\":\"2008\"},{\"1\":\"Chinstrap\",\"2\":\"Dream\",\"3\":\"54.2\",\"4\":\"20.8\",\"5\":\"201\",\"6\":\"4300\",\"7\":\"male\",\"8\":\"2008\"},{\"1\":\"Chinstrap\",\"2\":\"Dream\",\"3\":\"42.5\",\"4\":\"16.7\",\"5\":\"187\",\"6\":\"3350\",\"7\":\"female\",\"8\":\"2008\"},{\"1\":\"Chinstrap\",\"2\":\"Dream\",\"3\":\"51.0\",\"4\":\"18.8\",\"5\":\"203\",\"6\":\"4100\",\"7\":\"male\",\"8\":\"2008\"},{\"1\":\"Chinstrap\",\"2\":\"Dream\",\"3\":\"49.7\",\"4\":\"18.6\",\"5\":\"195\",\"6\":\"3600\",\"7\":\"male\",\"8\":\"2008\"},{\"1\":\"Chinstrap\",\"2\":\"Dream\",\"3\":\"47.5\",\"4\":\"16.8\",\"5\":\"199\",\"6\":\"3900\",\"7\":\"female\",\"8\":\"2008\"},{\"1\":\"Chinstrap\",\"2\":\"Dream\",\"3\":\"47.6\",\"4\":\"18.3\",\"5\":\"195\",\"6\":\"3850\",\"7\":\"female\",\"8\":\"2008\"},{\"1\":\"Chinstrap\",\"2\":\"Dream\",\"3\":\"52.0\",\"4\":\"20.7\",\"5\":\"210\",\"6\":\"4800\",\"7\":\"male\",\"8\":\"2008\"},{\"1\":\"Chinstrap\",\"2\":\"Dream\",\"3\":\"46.9\",\"4\":\"16.6\",\"5\":\"192\",\"6\":\"2700\",\"7\":\"female\",\"8\":\"2008\"},{\"1\":\"Chinstrap\",\"2\":\"Dream\",\"3\":\"53.5\",\"4\":\"19.9\",\"5\":\"205\",\"6\":\"4500\",\"7\":\"male\",\"8\":\"2008\"},{\"1\":\"Chinstrap\",\"2\":\"Dream\",\"3\":\"49.0\",\"4\":\"19.5\",\"5\":\"210\",\"6\":\"3950\",\"7\":\"male\",\"8\":\"2008\"},{\"1\":\"Chinstrap\",\"2\":\"Dream\",\"3\":\"46.2\",\"4\":\"17.5\",\"5\":\"187\",\"6\":\"3650\",\"7\":\"female\",\"8\":\"2008\"},{\"1\":\"Chinstrap\",\"2\":\"Dream\",\"3\":\"50.9\",\"4\":\"19.1\",\"5\":\"196\",\"6\":\"3550\",\"7\":\"male\",\"8\":\"2008\"},{\"1\":\"Chinstrap\",\"2\":\"Dream\",\"3\":\"45.5\",\"4\":\"17.0\",\"5\":\"196\",\"6\":\"3500\",\"7\":\"female\",\"8\":\"2008\"},{\"1\":\"Chinstrap\",\"2\":\"Dream\",\"3\":\"50.9\",\"4\":\"17.9\",\"5\":\"196\",\"6\":\"3675\",\"7\":\"female\",\"8\":\"2009\"},{\"1\":\"Chinstrap\",\"2\":\"Dream\",\"3\":\"50.8\",\"4\":\"18.5\",\"5\":\"201\",\"6\":\"4450\",\"7\":\"male\",\"8\":\"2009\"},{\"1\":\"Chinstrap\",\"2\":\"Dream\",\"3\":\"50.1\",\"4\":\"17.9\",\"5\":\"190\",\"6\":\"3400\",\"7\":\"female\",\"8\":\"2009\"},{\"1\":\"Chinstrap\",\"2\":\"Dream\",\"3\":\"49.0\",\"4\":\"19.6\",\"5\":\"212\",\"6\":\"4300\",\"7\":\"male\",\"8\":\"2009\"},{\"1\":\"Chinstrap\",\"2\":\"Dream\",\"3\":\"51.5\",\"4\":\"18.7\",\"5\":\"187\",\"6\":\"3250\",\"7\":\"male\",\"8\":\"2009\"},{\"1\":\"Chinstrap\",\"2\":\"Dream\",\"3\":\"49.8\",\"4\":\"17.3\",\"5\":\"198\",\"6\":\"3675\",\"7\":\"female\",\"8\":\"2009\"},{\"1\":\"Chinstrap\",\"2\":\"Dream\",\"3\":\"48.1\",\"4\":\"16.4\",\"5\":\"199\",\"6\":\"3325\",\"7\":\"female\",\"8\":\"2009\"},{\"1\":\"Chinstrap\",\"2\":\"Dream\",\"3\":\"51.4\",\"4\":\"19.0\",\"5\":\"201\",\"6\":\"3950\",\"7\":\"male\",\"8\":\"2009\"},{\"1\":\"Chinstrap\",\"2\":\"Dream\",\"3\":\"45.7\",\"4\":\"17.3\",\"5\":\"193\",\"6\":\"3600\",\"7\":\"female\",\"8\":\"2009\"},{\"1\":\"Chinstrap\",\"2\":\"Dream\",\"3\":\"50.7\",\"4\":\"19.7\",\"5\":\"203\",\"6\":\"4050\",\"7\":\"male\",\"8\":\"2009\"},{\"1\":\"Chinstrap\",\"2\":\"Dream\",\"3\":\"42.5\",\"4\":\"17.3\",\"5\":\"187\",\"6\":\"3350\",\"7\":\"female\",\"8\":\"2009\"},{\"1\":\"Chinstrap\",\"2\":\"Dream\",\"3\":\"52.2\",\"4\":\"18.8\",\"5\":\"197\",\"6\":\"3450\",\"7\":\"male\",\"8\":\"2009\"},{\"1\":\"Chinstrap\",\"2\":\"Dream\",\"3\":\"45.2\",\"4\":\"16.6\",\"5\":\"191\",\"6\":\"3250\",\"7\":\"female\",\"8\":\"2009\"},{\"1\":\"Chinstrap\",\"2\":\"Dream\",\"3\":\"49.3\",\"4\":\"19.9\",\"5\":\"203\",\"6\":\"4050\",\"7\":\"male\",\"8\":\"2009\"},{\"1\":\"Chinstrap\",\"2\":\"Dream\",\"3\":\"50.2\",\"4\":\"18.8\",\"5\":\"202\",\"6\":\"3800\",\"7\":\"male\",\"8\":\"2009\"},{\"1\":\"Chinstrap\",\"2\":\"Dream\",\"3\":\"45.6\",\"4\":\"19.4\",\"5\":\"194\",\"6\":\"3525\",\"7\":\"female\",\"8\":\"2009\"},{\"1\":\"Chinstrap\",\"2\":\"Dream\",\"3\":\"51.9\",\"4\":\"19.5\",\"5\":\"206\",\"6\":\"3950\",\"7\":\"male\",\"8\":\"2009\"},{\"1\":\"Chinstrap\",\"2\":\"Dream\",\"3\":\"46.8\",\"4\":\"16.5\",\"5\":\"189\",\"6\":\"3650\",\"7\":\"female\",\"8\":\"2009\"},{\"1\":\"Chinstrap\",\"2\":\"Dream\",\"3\":\"45.7\",\"4\":\"17.0\",\"5\":\"195\",\"6\":\"3650\",\"7\":\"female\",\"8\":\"2009\"},{\"1\":\"Chinstrap\",\"2\":\"Dream\",\"3\":\"55.8\",\"4\":\"19.8\",\"5\":\"207\",\"6\":\"4000\",\"7\":\"male\",\"8\":\"2009\"},{\"1\":\"Chinstrap\",\"2\":\"Dream\",\"3\":\"43.5\",\"4\":\"18.1\",\"5\":\"202\",\"6\":\"3400\",\"7\":\"female\",\"8\":\"2009\"},{\"1\":\"Chinstrap\",\"2\":\"Dream\",\"3\":\"49.6\",\"4\":\"18.2\",\"5\":\"193\",\"6\":\"3775\",\"7\":\"male\",\"8\":\"2009\"},{\"1\":\"Chinstrap\",\"2\":\"Dream\",\"3\":\"50.8\",\"4\":\"19.0\",\"5\":\"210\",\"6\":\"4100\",\"7\":\"male\",\"8\":\"2009\"},{\"1\":\"Chinstrap\",\"2\":\"Dream\",\"3\":\"50.2\",\"4\":\"18.7\",\"5\":\"198\",\"6\":\"3775\",\"7\":\"female\",\"8\":\"2009\"}],\"options\":{\"columns\":{\"min\":{},\"max\":[10]},\"rows\":{\"min\":[10],\"max\":[10]},\"pages\":{}}}\n  </script>\n</div>\n`````\n:::\n:::\n\n\n## Basic Plot\n\nA basic scatter plot, which we will progressively dress up.\n\n::: {.panel-tabset .nav-pills style=\"background: whitesmoke;\"}\n### Using ggformula\n\n\n::: {.cell hash='index_cache/html/unnamed-chunk-4_15f95500973b551f9e35237a7b4bdea8'}\n\n````{.cell-code}\n```{{r}}\n## simple plot: data + mappings + geometry\n## no colour or fill yet\ngf <-  gf_point(bill_depth_mm ~ bill_length_mm, \n                 data = penguins, \n                 alpha = 0.6, size = 3.5)\ngf\n```\n````\n\n::: {.cell-output-display}\n![](index_files/figure-html/unnamed-chunk-4-1.png){width=2100}\n:::\n:::\n\n\n### Using ggplot\n\n\n::: {.cell hash='index_cache/html/unnamed-chunk-5_eae45d9b62d36ab048a7e1b2d64cf5b2'}\n\n````{.cell-code}\n```{{r}}\n## simple plot: data + mappings + geometry\n## no colour or fill yet\ngg <- ggplot(penguins, aes(x = bill_length_mm,\n                           y = bill_depth_mm)) +\n  geom_point(alpha = .6, size = 3.5)\ngg\n```\n````\n\n::: {.cell-output-display}\n![](index_files/figure-html/unnamed-chunk-5-1.png){width=2100}\n:::\n:::\n\n:::\n\n## Customized Plot\n\nLet us set some ggplot theme aspects now!! Here is a handy picture\nshowing (most of) the theme-able aspects of a ggplot plot.\n\n![Rosana Ferrero (\\@RosanaFerrero) on Twitter Sept 11,\n2022](images/ggplot_theme_elements.jfif){fig-alt=\"Ggplot theme elements\"\nfig-align=\"center\"}\n\nFor more info, type `?theme` in your console.\n\n\n::: {.cell hash='index_cache/html/unnamed-chunk-6_be9e6174c9b9e6cf5275aee51fc91d29'}\n\n````{.cell-code}\n```{{r}}\n## change global theme settings (for all following plots)\nmy_theme <- theme_set(theme_classic(base_size = 12, \n                        base_family = \"roboto\"\n                        )) +  \n\n## modify plot elements globally (for all following plots)\ntheme_update(\n  axis.ticks = element_line(color = \"grey92\"),\n  axis.ticks.length = unit(.5, \"lines\"),\n  panel.grid.minor = element_blank(),\n  legend.title = element_text(size = 12),\n  legend.text = element_text(color = \"grey30\"),\n  plot.title = element_text(size = 18, face = \"bold\"),\n  plot.subtitle = element_text(size = 12, color = \"grey30\"),\n  plot.caption = element_text(size = 9, margin = margin(t = 15))\n)\n```\n````\n:::\n\n\nSince we know what the basic plot looks like, let's add titles, labels\nand colours. We will also set limits and scales.\n\n::: {.panel-tabset .nav-pills style=\"background: whitesmoke;\"}\n### Using ggformula\n\n\n::: {.cell hash='index_cache/html/unnamed-chunk-7_fd5b6e796fd5cb5a681ef2c167a0dee9'}\n\n````{.cell-code}\n```{{r}}\ntheme_set(my_theme)\n\ngf1 <- penguins %>% \n  gf_point(bill_depth_mm ~ bill_length_mm, \n           \n           # colour by continuous variable\n           color =  ~ body_mass_g, \n           alpha = .6, size = 3.5) %>% \n\n  \n  ## custom axes scaling\n  gf_refine(\n  scale_x_continuous(breaks = 3:6 * 10, limits = c(30, 60)),\n  scale_y_continuous(breaks = seq(12.5, 22.5, by = 2.5), \n                     limits = c(12.5, 22.5)), \n  \n  ## custom colors from the scico package\n  ## using the paletteer super package\n  paletteer:: scale_color_paletteer_c(`\"scico::bamako\"`, \n                                      direction = -1),\n  \n  ## custom labels\n  labs(\n    title = 'Bill Dimensions of Brush-Tailed Penguins (Pygoscelis)',\n    subtitle = 'A scatter plot of bill depth versus bill length.',\n    caption = 'Data: Gorman, Williams & Fraser (2014) PLoS ONE',\n    x = 'Bill Length (mm)', \n    y = 'Bill Depth (mm)',\n## See this!\n    color = 'Body mass (g)'\n  ))\n\ngf1\n```\n````\n\n::: {.cell-output-display}\n![](index_files/figure-html/unnamed-chunk-7-1.png){width=2100}\n:::\n:::\n\n\nNote this neat way of *naming a scale and the legend* in the `labs`\ncommand above!\n\n### Using ggplot\n\n\n::: {.cell hash='index_cache/html/unnamed-chunk-8_58facea8ed9f432079873a853ecc657c'}\n\n````{.cell-code}\n```{{r}}\ntheme_set(my_theme)\n\n\ngg1 <- penguins %>% \n  ggplot(aes(y = bill_depth_mm, x = bill_length_mm), \n         alpha = .6) +\n  geom_point(aes(colour = body_mass_g), size = 3.5) + \n\n  \n  ## custom axes scaling\n  scale_x_continuous(breaks = 3:6 * 10, limits = c(30, 60)) + \n  scale_y_continuous(breaks = seq(12.5, 22.5, by = 2.5), \n                     limits = c(12.5, 22.5)) + \n  \n  ## custom colors from the scico package\n  paletteer:: scale_color_paletteer_c(`\"scico::bamako\"`, \n                                      direction = -1) + \n  \n  ## custom labels\n  labs(\n    title = 'Bill Dimensions of Brush-Tailed Penguins (Pygoscelis)',\n    subtitle = 'A scatter plot of bill depth versus bill length.',\n    caption = 'Data: Gorman, Williams & Fraser (2014) PLoS ONE',\n    x = 'Bill Length (mm)', \n    y = 'Bill Depth (mm)',\n    color = 'Body mass (g)' \n  )\ngg1\n```\n````\n\n::: {.cell-output-display}\n![](index_files/figure-html/unnamed-chunk-8-1.png){width=2100}\n:::\n:::\n\n:::\n\n## Using {ggtext}\n\nFrom [Claus Wilke's website](https://wilkelab.org/ggtext/) \nwww.wilkelab.org/ggtext\n\n> The `ggtext` package provides simple Markdown and HTML rendering for\n> ggplot2. Under the hood, the package uses the `gridtext` package for\n> the actual rendering, and consequently it is limited to the feature\n> set provided by `gridtext`.\\\n> Support is provided for Markdown both in theme elements (plot titles,\n> subtitles, captions, axis labels, legends, etc.) and in geoms (similar\n> to `geom_text()`). In both cases, there are two alternatives, one for\n> creating simple text labels and one for creating text boxes with word\n> wrapping.\n\n::: callout-caution\n### Working with ggtext\n\nNOTE: on some machines, the `ggtext` package may not work as expected.\nIn this case, please do as follows, using your Console:\n\n-   remove gridtext: `remove.packages(gridtext)`.\n-   Install *development version* of `gridtext`:\n    `install.packages(remotes)`\n    `remotes::install_github(\"wilkelab/gridtext\")`\n:::\n\n### Using element_markdown()\n\nWe can use our familiar markdown syntax right inside the titles and\ncaptions of the plot. `element_markdown()` is a theme-ing command made\navailable by the `ggtext` package.\n\n`element_markdown()`  formatted text elements, e.g. titles, caption,\naxis text, striptext.\n\n::: {.panel-tabset .nav-pills style=\"background: whitesmoke;\"}\n### Using ggformula\n\n\n::: {.cell hash='index_cache/html/unnamed-chunk-9_1117cf4861c63482125bb3b1c756c490'}\n\n````{.cell-code}\n```{{r}}\ntheme_set(my_theme)\n\ngf2 <- penguins %>% gf_point(bill_depth_mm ~ bill_length_mm, \n                            color = ~ body_mass_g, \n                            alpha = 0.6, size = 3.5) %>% \n gf_refine(\n  scale_x_continuous(breaks = 3:6 * 10, limits = c(30, 60)),\n  scale_y_continuous(breaks = seq(12.5, 22.5, by = 2.5), \n                     limits = c(12.5, 22.5)), \n  \n  ## custom colors from the scico package\n  paletteer:: scale_color_paletteer_c(\"scico::bamako\", \n                                      direction = -1),\n  \n  ## custom labels using element_markdown()\n   labs(\n    title = 'Bill Dimensions of Brush-Tailed Penguins (*Pygoscelis*)',\n    subtitle = 'A scatter plot of bill depth versus bill length.',\n    caption = 'Data: Gorman, Williams & Fraser (2014) *PLoS ONE*',\n    x = '**Bill Length** (mm)', \n    y = '**Bill Depth** (mm)',\n    color = 'Body mass (g)')\n  ) %>% \n  \n  # New code from here\n  # Enables markdown titles, captions and labels\n  gf_theme(theme(\n    plot.title = ggtext::element_markdown(),\n    plot.caption = ggtext::element_markdown(),\n    axis.title.x = ggtext::element_markdown(),\n    axis.title.y = ggtext::element_markdown()\n  ))\n\n gf2\n```\n````\n\n::: {.cell-output-display}\n![](index_files/figure-html/unnamed-chunk-9-1.png){width=2100}\n:::\n:::\n\n\n### Using ggplot\n\n\n::: {.cell hash='index_cache/html/unnamed-chunk-10_dc94217ad05607fc966351d7ac996389'}\n\n````{.cell-code}\n```{{r}}\ntheme_set(my_theme)\n\ngg2 <- ggplot(penguins, aes(x = bill_length_mm, y = bill_depth_mm)) +\n  geom_point(aes(color = body_mass_g), alpha = .6, size = 3.5) + \n  \n  scale_x_continuous(breaks = 3:6 * 10, limits = c(30, 60)) +\n  scale_y_continuous(breaks = seq(12.5, 22.5, by = 2.5), \n                     limits = c(12.5, 22.5)) +\n  paletteer:: scale_color_paletteer_c(`\"scico::bamako\"`, \n                                       direction = -1) +\n   \n  ## New code starts here: Two Step Procedure with ggtext\n  ## 1. Markdown formatting of labels and title, using asterisks\n  labs(\n    title = 'Bill Dimensions of Brush-Tailed Penguins (*Pygoscelis*)',\n    subtitle = 'A scatter plot of bill depth versus bill length.',\n    caption = 'Data: Gorman, Williams & Fraser (2014) *PLoS ONE*',\n    x = '**Bill Length** (mm)', \n    y = '**Bill Depth** (mm)',\n    color = 'Body mass (g)'\n  ) +\n   \n  ## 2. Add theme related commands from ggtext\n  ## render respective text elements\n  theme(\n    plot.title = ggtext::element_markdown(),\n    plot.caption = ggtext::element_markdown(),\n    axis.title.x = ggtext::element_markdown(),\n    axis.title.y = ggtext::element_markdown()\n  )\ngg2\n```\n````\n\n::: {.cell-output-display}\n![](index_files/figure-html/unnamed-chunk-10-1.png){width=2100}\n:::\n:::\n\n:::\n\n### `element_markdown()` in combination with HTML\n\nThis allows us to change fonts in titles, labels, and captions.\n\n::: {.panel-tabset .nav-pills style=\"background: whitesmoke;\"}\n\n### Using ggformula\n\n\n::: {.cell layout-ncol=\"2\" hash='index_cache/html/unnamed-chunk-11_90caff2e409001c08c5bdbac27586ee6'}\n\n````{.cell-code}\n```{{r}}\n#| layout-ncol: 2\n\ntheme_set(my_theme)\n\n## use HTML syntax to change text color\n\ngf2 %>% \n  \n  # html in labels\n  gf_labs(title = 'Bill Dimensions of Brush-Tailed Penguins\n          <i style = \"color:#28A87D;\">Pygoscelis </i>'\n            ) \n\n\n## use HTML syntax to change font and text size\ngf2 %>% \n  gf_labs(title = 'Bill Dimensions of Brush-Tailed Penguins <b style=\"font-size:32pt;font-family:tangerine;\">Pygoscelis</b>') \n```\n````\n\n::: {.cell-output-display}\n![](index_files/figure-html/unnamed-chunk-11-1.png){width=2100}\n:::\n\n::: {.cell-output-display}\n![](index_files/figure-html/unnamed-chunk-11-2.png){width=2100}\n:::\n:::\n\n\n### Using ggplot\n\n\n::: {.cell layout-ncol=\"2\" hash='index_cache/html/unnamed-chunk-12_780be3cf35ab84babb1530f7b9536cf2'}\n\n````{.cell-code}\n```{{r}}\n#| layout-ncol: 2\n\ntheme_set(my_theme)\n\n## use HTML syntax to change text color\ngg2 +\n  labs(title = 'Bill Dimensions of Brush-Tailed Penguins <i style=\"color:#28A87D;\">Pygoscelis</i>') +\n  theme(plot.margin = margin(t = 15))\n\n\n## use HTML syntax to change font and text size\ngg2 +\n  labs(title = 'Bill Dimensions of Brush-Tailed Penguins <b style=\"font-size:32pt;font-family:tangerine;\">Pygoscelis</b>')\n```\n````\n\n::: {.cell-output-display}\n![](index_files/figure-html/unnamed-chunk-12-1.png){width=2100}\n:::\n\n::: {.cell-output-display}\n![](index_files/figure-html/unnamed-chunk-12-2.png){width=2100}\n:::\n:::\n\n:::\n\n### Adding images to ggplot{.hidden}\n\nSave an image from the web in the same folder as your RMarkdown. Use\nhtml tags to include it, say as part of your plot title, as shown below.\n\n::: {.panel-tabset .nav-pills style=\"background: whitesmoke;\"}\n\n### Using ggformula\n\n\n::: {.cell hash='index_cache/html/unnamed-chunk-13_6be52af4af58feb8126d505e1c3a98e6'}\n\n````{.cell-code}\n```{{r}}\ntheme_set(my_theme)\n\n## use HTML syntax to add images to text elements\ngf2 %>% \n  gf_labs(title = 'Bill Dimensions of Brush-Tailed Penguins &nbsp;&nbsp;&nbsp; < img src=\"images/culmen_depth.png\" width=\"480\"/>') \n```\n````\n\n::: {.cell-output-display}\n![](index_files/figure-html/unnamed-chunk-13-1.png){width=2100}\n:::\n:::\n\n\n### Using ggplot\n\n\n::: {.cell hash='index_cache/html/unnamed-chunk-14_89542b70b394022669744f70412ca54b'}\n\n````{.cell-code}\n```{{r}}\ntheme_set(my_theme)\n\n## use HTML syntax to add images to text elements\ngg2 + \n  labs(title = 'Bill Dimensions of Brush-Tailed Penguins &nbsp;&nbsp;&nbsp; <img src=\"images/culmen_depth.png\" width=\"480\"/>')\n```\n````\n\n::: {.cell-output-display}\n![](index_files/figure-html/unnamed-chunk-14-1.png){width=2100}\n:::\n:::\n\n:::\n\n\n### Annotations with `geom_richtext()` and `geom_textbox()`\n\nFurther ggplot annotations can be achieved using `geom_richtext()` and\n`geom_textbox()`. `geom_richtext()` also allows formatted text labels\nwith 360 rotation. One needs to pass a tibble to `geom_richtext()`\ngiving the location, colour, rotation etc of the label annotation.\n\n::: {.panel-tabset .nav-pills style=\"background: whitesmoke;\"}\n### Design the labels\n\n\n::: {.cell code-annotation='below' hash='index_cache/html/unnamed-chunk-15_5874a7119bac5f1eda7c81811cd5a6b7'}\n\n````{.cell-code}\n```{{r}}\n#| code-annotation: below\n# Create a label tibble\n# Three rich text labels, \n# so three sets of locations x and y, and angle of rotation\n\nlabels <- tibble(\n      x = c(34, 56, 54), \n      y = c(20, 18.5, 14.5),\n      angle = c(12, 20, 335),\n      species = c(\"Adelie\", \"Chinstrap\", \"Gentoo\"),\n      \n      lab = c(\"<b style='font-family:anton;font-size:24pt;'>Adlie</b><br><i style='color:darkgrey;'>P. adliae</i>\", \n              \"<b style='font-family:anton;font-size:24pt;'>Chinstrap</b><br><i style='color:darkgrey;'>P. antarctica</i>\", \n              \"<b style='font-family:anton;font-size:24pt;'>Gentoo</b><br><i style='color:darkgrey;'>P. papua</i>\"))\nlabels\n```\n````\n\n::: {.cell-output-display}\n`````{=html}\n<div data-pagedtable=\"false\">\n  <script data-pagedtable-source type=\"application/json\">\n{\"columns\":[{\"label\":[\"x\"],\"name\":[1],\"type\":[\"dbl\"],\"align\":[\"right\"]},{\"label\":[\"y\"],\"name\":[2],\"type\":[\"dbl\"],\"align\":[\"right\"]},{\"label\":[\"angle\"],\"name\":[3],\"type\":[\"dbl\"],\"align\":[\"right\"]},{\"label\":[\"species\"],\"name\":[4],\"type\":[\"chr\"],\"align\":[\"left\"]},{\"label\":[\"lab\"],\"name\":[5],\"type\":[\"chr\"],\"align\":[\"left\"]}],\"data\":[{\"1\":\"34\",\"2\":\"20.0\",\"3\":\"12\",\"4\":\"Adelie\",\"5\":\"<b style='font-family:anton;font-size:24pt;'>Adlie<\\/b><br><i style='color:darkgrey;'>P. adliae<\\/i>\"},{\"1\":\"56\",\"2\":\"18.5\",\"3\":\"20\",\"4\":\"Chinstrap\",\"5\":\"<b style='font-family:anton;font-size:24pt;'>Chinstrap<\\/b><br><i style='color:darkgrey;'>P. antarctica<\\/i>\"},{\"1\":\"54\",\"2\":\"14.5\",\"3\":\"335\",\"4\":\"Gentoo\",\"5\":\"<b style='font-family:anton;font-size:24pt;'>Gentoo<\\/b><br><i style='color:darkgrey;'>P. papua<\\/i>\"}],\"options\":{\"columns\":{\"min\":{},\"max\":[10]},\"rows\":{\"min\":[10],\"max\":[10]},\"pages\":{}}}\n  </script>\n</div>\n`````\n:::\n:::\n\n\n### Using ggformula\n\n\n::: {.cell hash='index_cache/html/unnamed-chunk-16_8e828e68aa03d7a3e8b6a0aa4e582a19'}\n\n````{.cell-code}\n```{{r}}\ntheme_set(my_theme)\n\ngf_rich <- penguins %>% \n  gf_point(bill_depth_mm ~ bill_length_mm, \n                      color = ~ species, \n                      alpha = 0.6, size = 3.5, data = penguins) +\n  \n  \n    ## add text annotations for each species\n    ggtext::geom_richtext(\n    data = labels,\n    # Now pass the data variables as aesthetics\n    aes(x, y, label = lab, color = species, angle = angle), \n    size = 4, fill = NA, label.color = NA,\n    lineheight = .3) +\n    # show.legend = FALSE else we get some unusual legends!\n    # fill = NA makes the labels' fill transparent\n  \n  \n  scale_x_continuous(breaks = 3:6 * 10, limits = c(30, 60)) +\n  scale_y_continuous(breaks = seq(12.5, 22.5, by = 2.5), \n                     limits = c(12.5, 22.5)) +\n  scale_colour_paletteer_d(palette = `\"rcartocolor::Bold\"`, \n                           guide = \"none\") +\n  \n  labs(\n    title = 'Bill Dimensions of Brush-Tailed Penguins (*Pygoscelis*)',\n    subtitle = 'A scatter plot of bill depth versus bill length.',\n    caption = 'Data: Gorman, Williams & Fraser (2014) *PLoS ONE*',\n    x = '**Bill Length** (mm)', \n    y = '**Bill Depth** (mm)',\n    color = 'Body mass (g)'\n  ) +\n  \n  # Use theme and element_markdown() to format axes and titles as usual\n  theme(\n    plot.title = ggtext::element_markdown(),\n    plot.caption = ggtext::element_markdown(),\n    axis.title.x = ggtext::element_markdown(),\n    axis.title.y = ggtext::element_markdown(),\n    plot.margin = margin(25, 6, 15, 6)\n  )\n\n\ngf_rich\n```\n````\n\n::: {.cell-output-display}\n![](index_files/figure-html/unnamed-chunk-16-1.png){width=2100}\n:::\n:::\n\n\n::: callout-important\nNote the plus sign usage here!!We are combining the ggformula and ggplot\nsyntax, and it works!\n:::\n\n### Using ggplot\n\n\n::: {.cell hash='index_cache/html/unnamed-chunk-17_3451d8d5a1eee9e9732b1c25da891c7a'}\n\n````{.cell-code}\n```{{r}}\ntheme_set(my_theme)\n\n\ngg_rich <- ggplot(penguins, aes(x = bill_length_mm, \n                                y = bill_depth_mm)) +\n  geom_point(aes(color = species), alpha = .6, size = 3.5) + \n  \n  ## add text annotations for each species\n  ggtext::geom_richtext(\n    data = labels,\n    # Now pass the data variables as aesthetics\n    aes(x, y, label = lab, color = species, angle = angle), \n    size = 4, fill = NA, label.color = NA,\n    lineheight = .3) +\n  \n  \n  scale_x_continuous(breaks = 3:6 * 10, limits = c(30, 60)) +\n  scale_y_continuous(breaks = seq(12.5, 22.5, by = 2.5), \n                     limits = c(12.5, 22.5)) +\n  scale_colour_paletteer_d(`\"rcartocolor::Bold\"`, guide = \"none\")+\n  \n  labs(\n    title = 'Bill Dimensions of Brush-Tailed Penguins (*Pygoscelis*)',\n    subtitle = 'A scatter plot of bill depth versus bill length.',\n    caption = 'Data: Gorman, Williams & Fraser (2014) *PLoS ONE*',\n    x = '**Bill Length** (mm)', \n    y = '**Bill Depth** (mm)',\n    color = 'Body mass (g)'\n  ) +\n  \n  # Use theme and element_markdown() to format axes and titles as usual\n  theme(\n    plot.title = ggtext::element_markdown(),\n    plot.caption = ggtext::element_markdown(),\n    axis.title.x = ggtext::element_markdown(),\n    axis.title.y = ggtext::element_markdown(),\n    plot.margin = margin(25, 6, 15, 6)\n  )\n  \ngg_rich\n```\n````\n\n::: {.cell-output-display}\n![](index_files/figure-html/unnamed-chunk-17-1.png){width=2100}\n:::\n:::\n\n:::\n\n### Formatted Text boxes on plots\n\n`element_textbox()` and `element_textbox_simple()`  formatted text\nboxes with word wrapping.\n\n::: {.panel-tabset .nav-pills style=\"background: whitesmoke;\"}\n### Using ggformula\n\n\n::: {.cell hash='index_cache/html/unnamed-chunk-18_95de9a91134ae221ac68215bfe5778d1'}\n\n````{.cell-code}\n```{{r}}\ntheme_set(my_theme)\n\ngf_box <- penguins %>% \n  gf_point(bill_depth_mm ~ bill_length_mm, \n                      color = ~ species, \n                      alpha = 0.6, size = 3.5, data = penguins) +\n  \n  \n    ## add text annotations for each species\n    ggtext::geom_richtext(\n    data = labels,\n    # Now pass the data variables as aesthetics\n    aes(x, y, label = lab, color = species, angle = angle), \n    size = 4, fill = NA, label.color = NA,\n    lineheight = .3) +\n    # show.legend = FALSE else we get some unusual legends!\n    # fill = NA makes the labels' fill transparent\n  \n  \n  scale_x_continuous(breaks = 3:6 * 10, limits = c(30, 60)) +\n  scale_y_continuous(breaks = seq(12.5, 22.5, by = 2.5), \n                     limits = c(12.5, 22.5)) +\n  scale_colour_paletteer_d(palette = `\"rcartocolor::Bold\"`, \n                           guide = \"none\") +\n  \n  \n# Now for the Plot Titles and Labels, as before  \n  labs(\n    title = 'Bill Dimensions of Brush-Tailed Penguins (*Pygoscelis*)',\n    subtitle = 'A scatter plot of bill depth versus bill length.',\n    caption = 'Data: Gorman, Williams & Fraser (2014) *PLoS ONE*',\n    x = '**Bill Length** (mm)',\n    y = '**Bill Depth** (mm)',\n    color = 'Body mass (g)'\n  ) +\n  \n# Add the ggtext theme related commands\n  theme(\n    ## turn title into filled textbox\n    plot.title = ggtext::element_textbox_simple(\n      color = \"white\",\n      fill = \"#28A78D\",\n      size = 28,\n      padding = margin(8, 4, 8, 4),\n      margin = margin(b = 5),\n      lineheight = .9\n    ),\n    plot.subtitle = ggtext::element_textbox_simple(\n      size = 10,\n      padding = margin(5.5, 5.5, 5.5, 5.5),\n      margin = margin(0, 0, 5.5, 0),\n      fill = \"orange1\"\n    ),\n    \n    ## add round outline to caption\n    plot.caption = ggtext::element_textbox_simple(\n      width = NULL,\n      linetype = 1,\n      fill = \"grey\",\n      padding = margin(4, 8, 4, 8),\n      margin = margin(t = 15),\n      r = grid::unit(8, \"pt\")\n    ),\n    axis.title.x = ggtext::element_markdown(),\n    axis.title.y = ggtext::element_markdown(),\n    plot.margin = margin(25, 6, 15, 6)\n  )\n\ngf_box\n```\n````\n\n::: {.cell-output-display}\n![](index_files/figure-html/unnamed-chunk-18-1.png){width=2100}\n:::\n:::\n\n\n### Using ggplot\n\n\n::: {.cell hash='index_cache/html/unnamed-chunk-19_55b774d54d643297130e92ccfcd0f30c'}\n\n````{.cell-code}\n```{{r}}\ntheme_set(my_theme)\n\ngg_box <- ggplot(penguins, \n                 aes(x = bill_length_mm, y = bill_depth_mm)) +\n  geom_point(aes(color = species), \n             alpha = .6, size = 3.5) +\n  \n     ## add text annotations for each species\n  ggtext::geom_richtext(data = labels,\n    # Now pass the data variables as aesthetics\n    aes(x, y, label = lab, color = species, angle = angle), \n    size = 4, fill = NA, label.color = NA,\n    lineheight = .3) +\n    # show.legend = FALSE else we get some unusual legends!\n    # fill = NA makes the labels' fill transparent\n  \n  \n  scale_x_continuous(breaks = 3:6 * 10, limits = c(30, 60)) +\n  scale_y_continuous(breaks = seq(12.5, 22.5, by = 2.5), \n                     limits = c(12.5, 22.5)) +\n  scale_colour_paletteer_d(palette = `\"rcartocolor::Bold\"`, \n                           guide = \"none\") +\n  \n  \n# Now for the Plot Titles and Labels, as before  \n  labs(\n    title = 'Bill Dimensions of Brush-Tailed Penguins (*Pygoscelis*)',\n    subtitle = 'A scatter plot of bill depth versus bill length.',\n    caption = 'Data: Gorman, Williams & Fraser (2014) *PLoS ONE*',\n    x = '**Bill Length** (mm)',\n    y = '**Bill Depth** (mm)',\n    color = 'Body mass (g)'\n  ) +\n  \n# Add the ggtext theme related commands\n  theme(\n    ## turn title into filled textbox\n    plot.title = ggtext::element_textbox_simple(\n      color = \"white\",\n      fill = \"#28A78D\",\n      size = 28,\n      padding = margin(8, 4, 8, 4),\n      margin = margin(b = 5),\n      lineheight = .9\n    ),\n    plot.subtitle = ggtext::element_textbox_simple(\n      size = 10,\n      padding = margin(5.5, 5.5, 5.5, 5.5),\n      margin = margin(0, 0, 5.5, 0),\n      fill = \"orange1\"\n    ),\n    \n    ## add round outline to caption\n    plot.caption = ggtext::element_textbox_simple(\n      width = NULL,\n      linetype = 1,\n      fill = \"grey\",\n      padding = margin(4, 8, 4, 8),\n      margin = margin(t = 15),\n      r = grid::unit(8, \"pt\")\n    ),\n    axis.title.x = ggtext::element_markdown(),\n    axis.title.y = ggtext::element_markdown(),\n    plot.margin = margin(25, 6, 15, 6)\n  )\n\ngg_box\n```\n````\n\n::: {.cell-output-display}\n![](index_files/figure-html/unnamed-chunk-19-1.png){width=2100}\n:::\n:::\n\n:::\n\n### Using `geom_texbox()` for formatted text boxes with word wrapping\n\n::: {.panel-tabset .nav-pills style=\"background: whitesmoke;\"}\n\n### Using ggformula\n\n\n::: {.cell hash='index_cache/html/unnamed-chunk-20_c12223280b1665b145ba2448896ade1d'}\n\n````{.cell-code}\n```{{r}}\ntheme_set(my_theme)\n\ntext_box <- tibble(x = 34, y = 13.7, label = \"<span style='font-size:12pt;font-family:anton;'>Lorem Ipsum Dolor Sit Amet</span><br><br>Lorem ipsum dolor sit amet, consectetur adipiscing elit, sed do eiusmod tempor incididunt ut labore et dolore magna aliqua. Ut enim ad minim veniam, quis nostrud exercitation ullamco laboris nisi ut aliquip ex ea commodo consequat. Duis aute irure dolor in reprehenderit in voluptate velit esse cillum dolore eu fugiat nulla pariatur. Excepteur sint occaecat cupidatat non proident, sunt in culpa qui officia deserunt mollit anim id est laborum.\")\n\n\ngf_box +\n  ## add textbox with long paragraphs\n  ggtext::geom_textbox(\n    data = text_box,\n    aes(x, y, \n        label = label),\n    size = 2.2, family = \"sans\",\n    fill = \"cornsilk\", \n    \n    colour = \"black\",\n# This is ESSENTIAL !!!\n# It appears that the original colour aesthetic mapping in `gf_box` and a possible colour aesthetic with `geom_textbox` have a clash, *only* with ggformula. No such issues below with the ggplot.\n# So declaring a colour here is essential\n\n    box.color = \"cornsilk3\",\n    #box.padding = c(2,2,2,2),\n    width = unit(11, \"lines\")\n  ) +\n  coord_cartesian(clip = \"off\") # ensure no clipping of labels near the edge\n```\n````\n\n::: {.cell-output-display}\n![](index_files/figure-html/unnamed-chunk-20-1.png){width=2100}\n:::\n:::\n\n\n### Using ggplot\n\n\n::: {.cell hash='index_cache/html/unnamed-chunk-21_647117c28fc75576ab964d5dbd24fcd5'}\n\n````{.cell-code}\n```{{r}}\ntheme_set(my_theme)\n\ngg_box +\n  ## add textbox with long paragraphs\n  ggtext::geom_textbox(\n    data = text_box,\n    aes(x, y, label = label),\n    size = 2.2, family = \"sans\",\n    fill = \"cornsilk\", box.color = \"cornsilk3\",\n    width = unit(11, \"lines\")\n  ) +\n  coord_cartesian(clip = \"off\") # ensure no clipping of labels near the edge\n```\n````\n\n::: {.cell-output-display}\n![](index_files/figure-html/unnamed-chunk-21-1.png){width=2100}\n:::\n:::\n\n:::\n\n### Using `{ggforce}`\n\nFrom [Thomas Lin Pedersen's website](www.ggforce.data-imaginist.com) \nwww.ggforce.data-imaginist.com\n\n> `ggforce` is a package aimed at providing missing functionality to\n> `ggplot2` through the extension system introduced with `ggplot2`\n> v2.0.0. Broadly speaking `ggplot2` has been aimed primarily at\n> explorative data visualization in order to investigate the data at\n> hand, and less at providing utilities for composing custom plots a la\n> `D3.js`. `ggforce` is mainly an attempt to address these \"shortcomings\"\n> (design choices might be a better description). The goal is to provide\n> a repository of geoms, stats, etc. that are as well documented and\n> implemented as the official ones found in `ggplot2`.\n\nWe will start with the basic plot, with the `ggtext` related work done\nup to now:\n\n\n::: {.cell hash='index_cache/html/unnamed-chunk-22_79f2154c21a7f1706a2007bd0ba832a9'}\n\n````{.cell-code}\n```{{r}}\n## use ggtext rendering for the following plots\ntheme_set(my_theme)\ntheme_update(\n  plot.title = ggtext::element_markdown(),\n  plot.caption = ggtext::element_markdown(),\n  axis.title.x = ggtext::element_markdown(),\n  axis.title.y = ggtext::element_markdown()\n)\n```\n````\n:::\n\n\n::: {.panel-tabset .nav-pills style=\"background: whitesmoke;\"}\n\n### Using ggformula and ggforce\n\n\n::: {.cell hash='index_cache/html/unnamed-chunk-23_09d649875693271908444c178642ca7a'}\n\n````{.cell-code}\n```{{r}}\ntheme_set(my_theme)\ntheme_update(\n  plot.title = ggtext::element_markdown(),\n  plot.caption = ggtext::element_markdown(),\n  axis.title.x = ggtext::element_markdown(),\n  axis.title.y = ggtext::element_markdown()\n)\n  \n## plot that we will annotate with ggforce afterwards\ngf3 <- penguins %>% \n  gf_point(bill_depth_mm ~ bill_length_mm,\n           color = ~ body_mass_g,\n           alpha = .6, \n           size = 3.5) + \n  \n  coord_cartesian(xlim = c(25, 65), ylim = c(10, 25)) +\n  \n  # Add Colour scales\n  scale_color_paletteer_c(`\"grDevices::Lajolla\"`, \n                          direction = -1) +\n  \n  # Add labels\n  labs(\n    title = \"Bill Dimensions of Brush-Tailed Penguins (*Pygoscelis*)\",\n    subtitle = 'A scatter plot of bill depth versus bill length.',\n    caption = \"Data: Gorman, Williams & Fraser (2014) *PLoS ONE*\",\n    x = \"**Bill Length** (mm)\",\n    y = \"**Bill Depth** (mm)\",\n    color = \"Body mass (g)\",\n    fill = \"Species\"\n  )\n\n\n\n## ellipsoids for all groups\ngf3 +\n  ggforce::geom_mark_ellipse(\n    aes(fill = species, \n        label = species), \n    \n    color = \"black\", \n    # This is good to include\n    # Else ellipses get coloured too\n    \n    alpha = .15, \n    show.legend = FALSE\n  ) \n```\n````\n\n::: {.cell-output-display}\n![](index_files/figure-html/unnamed-chunk-23-1.png){width=2100}\n:::\n:::\n\n\n### Using ggplot and ggforce\n\n\n::: {.cell hash='index_cache/html/unnamed-chunk-24_00c3063a0e31e506a87a8609d894f836'}\n\n````{.cell-code}\n```{{r}}\ntheme_set(my_theme)\ntheme_update(\n  plot.title = ggtext::element_markdown(),\n  plot.caption = ggtext::element_markdown(),\n  axis.title.x = ggtext::element_markdown(),\n  axis.title.y = ggtext::element_markdown()\n)\n\n## plot that we will annotate with ggforce afterwards\ngg3 <- ggplot(penguins, \n              aes(x = bill_length_mm, y = bill_depth_mm)) +\n  geom_point(aes(color = body_mass_g), \n             alpha = .6, \n             size = 3.5) + \n\n  coord_cartesian(xlim = c(25, 65), ylim = c(10, 25)) +\n  \n  # Add Colour scales\n  scale_color_paletteer_c(`\"grDevices::Lajolla\"`, \n                          direction = -1) +\n\n  \n  # Add labels\n  labs(\n    title = \"Bill Dimensions of Brush-Tailed Penguins (*Pygoscelis*)\",\n    subtitle = 'A scatter plot of bill depth versus bill length.',\n    caption = \"Data: Gorman, Williams & Fraser (2014) *PLoS ONE*\",\n    x = \"**Bill Length** (mm)\",\n    y = \"**Bill Depth** (mm)\",\n    color = \"Body mass (g)\",\n    fill = \"Species\"\n  )\n\n\n## ellipsoids for all groups\ngg3 +\n  ggforce::geom_mark_ellipse(\n    aes(fill = species, \n        label = species), \n    alpha = .15, \n    show.legend = FALSE\n  ) \n```\n````\n\n::: {.cell-output-display}\n![](index_files/figure-html/unnamed-chunk-24-1.png){width=2100}\n:::\n:::\n\n::: {.cell hash='index_cache/html/unnamed-chunk-25_9364534ce5a7692bc384764bb2e96b05'}\n\n````{.cell-code}\n```{{r}}\ntheme_set(my_theme)\ntheme_update(\n  plot.title = ggtext::element_markdown(),\n  plot.caption = ggtext::element_markdown(),\n  axis.title.x = ggtext::element_markdown(),\n  axis.title.y = ggtext::element_markdown()\n)\n\n## ellipsoids for specific subset\ngg3 +\n  ggforce::geom_mark_ellipse(\n    aes(fill = species, label = species, \n        filter = species == 'Gentoo'), \n    alpha = 0, show.legend = FALSE\n  ) +\n geom_point(aes(color = body_mass_g), alpha = .6, size = 3.5)\n```\n````\n\n::: {.cell-output-display}\n![](index_files/figure-html/unnamed-chunk-25-1.png){width=2100}\n:::\n:::\n\n::: {.cell hash='index_cache/html/unnamed-chunk-26_4fc8c1e4cd5666b416b9785fa22565c2'}\n\n````{.cell-code}\n```{{r}}\ntheme_set(my_theme)\ntheme_update(\n  plot.title = ggtext::element_markdown(),\n  plot.caption = ggtext::element_markdown(),\n  axis.title.x = ggtext::element_markdown(),\n  axis.title.y = ggtext::element_markdown()\n)\n\n## circles\ngg3 +\n  ggforce::geom_mark_circle(\n    aes(fill = species, label = species, \n        filter = species == 'Gentoo'), \n    alpha = 0, show.legend = FALSE\n  ) +\n  geom_point(aes(color = body_mass_g), alpha = .6, size = 3.5)\n```\n````\n\n::: {.cell-output-display}\n![](index_files/figure-html/unnamed-chunk-26-1.png){width=2100}\n:::\n:::\n\n::: {.cell hash='index_cache/html/unnamed-chunk-27_c0ebf339c9a92bec58e6765e3895012b'}\n\n````{.cell-code}\n```{{r}}\ntheme_set(my_theme)\ntheme_update(\n  plot.title = ggtext::element_markdown(),\n  plot.caption = ggtext::element_markdown(),\n  axis.title.x = ggtext::element_markdown(),\n  axis.title.y = ggtext::element_markdown()\n)\n\n## rectangles\ngg3 +\n  ggforce::geom_mark_rect(\n    aes(fill = species, label = species, \n        filter = species == 'Gentoo'), \n    alpha = 0, show.legend = FALSE\n  ) +\n  geom_point(aes(color = body_mass_g), alpha = .6, size = 3.5) \n```\n````\n\n::: {.cell-output-display}\n![](index_files/figure-html/unnamed-chunk-27-1.png){width=2100}\n:::\n:::\n\n::: {.cell hash='index_cache/html/unnamed-chunk-28_303ef94897faee5040d5b74a7054c666'}\n\n````{.cell-code}\n```{{r}}\ntheme_set(my_theme)\ntheme_update(\n  plot.title = ggtext::element_markdown(),\n  plot.caption = ggtext::element_markdown(),\n  axis.title.x = ggtext::element_markdown(),\n  axis.title.y = ggtext::element_markdown()\n)\n\n## hull\ngg3 +\n  ggforce::geom_mark_hull(\n    aes(fill = species, label = species, \n        filter = species == 'Gentoo'), \n    alpha = 0, show.legend = FALSE\n  ) +\n  geom_point(aes(color = body_mass_g), alpha = .6, size = 3.5)\n```\n````\n\n::: {.cell-output-display}\n![](index_files/figure-html/unnamed-chunk-28-1.png){width=2100}\n:::\n:::\n\n:::\n\n### ggplot tricks\n\n\n::: {.cell hash='index_cache/html/unnamed-chunk-29_77f64ebd3cf1f6b54f8f9161e988b812'}\n\n````{.cell-code}\n```{{r}}\ntheme_set(my_theme)\ntheme_update(\n  plot.title = ggtext::element_markdown(),\n  plot.caption = ggtext::element_markdown(),\n  axis.title.x = ggtext::element_markdown(),\n  axis.title.y = ggtext::element_markdown(),\n  legend.title = ggtext::element_markdown()\n)\n\ngg0 <-\n  ggplot(penguins, aes(x = bill_length_mm, y = bill_depth_mm)) +\n  ggforce::geom_mark_ellipse(aes(fill = species,\n                                 label = species),\n                             alpha = .15,\n                             show.legend = FALSE) +\n  geom_point(aes(color = body_mass_g), alpha = .6, size = 3.5) +\n  \n  scale_x_continuous(breaks = seq(25, 65, by = 5), \n                     limits = c(25, 65)) +\n  scale_y_continuous(breaks = seq(12, 24, by = 2), \n                     limits = c(12, 24)) +\n  \n  scico::scale_color_scico(palette = \"bamako\", direction = -1) +\n  labs(\n    title = \"**Bill Dimensions of Brush-Tailed Penguins** (*Pygoscelis*)\",\n    subtitle = 'A scatter plot of bill depth versus bill length.',\n    caption = \"Data: Gorman, Williams & Fraser (2014) *PLoS ONE*\",\n    x = \"**Bill Length** (mm)\",\n    y = \"**Bill Depth** (mm)\",\n    color = \"**Body mass** (g)\"\n  )\ngg0\n```\n````\n\n::: {.cell-output-display}\n![](index_files/figure-html/unnamed-chunk-29-1.png){width=2100}\n:::\n:::\n\n\n#### Left-Aligned Title\n\n\n::: {.cell hash='index_cache/html/unnamed-chunk-30_fe1d6126b337679b929bbd7fa7f75bbd'}\n\n````{.cell-code}\n```{{r}}\ntheme_set(my_theme)\ntheme_update(\n  plot.title = ggtext::element_markdown(),\n  plot.caption = ggtext::element_markdown(),\n  axis.title.x = ggtext::element_markdown(),\n  axis.title.y = ggtext::element_markdown(),\n  legend.title = ggtext::element_markdown()\n)\n\n(gg1 <- gg0 + theme(plot.title.position = \"plot\"))\n```\n````\n\n::: {.cell-output-display}\n![](index_files/figure-html/unnamed-chunk-30-1.png){width=2100}\n:::\n:::\n\n\n#### Right-Aligned Caption\n\n\n::: {.cell hash='index_cache/html/unnamed-chunk-31_b3d6ffc644cabae32c6611723da4840c'}\n\n````{.cell-code}\n```{{r}}\ntheme_set(my_theme)\ntheme_update(\n  plot.title = ggtext::element_markdown(),\n  plot.caption = ggtext::element_markdown(),\n  axis.title.x = ggtext::element_markdown(),\n  axis.title.y = ggtext::element_markdown(),\n  legend.title = ggtext::element_markdown()\n)\n\ngg1b <- gg1 +  theme(plot.caption.position = \"plot\")\ngg1b\n```\n````\n\n::: {.cell-output-display}\n![](index_files/figure-html/unnamed-chunk-31-1.png){width=2100}\n:::\n:::\n\n\n#### Legend Design\n\n\n::: {.cell layout-ncol=\"2\" hash='index_cache/html/unnamed-chunk-32_61ba2105ffd15fe9a9700e94e17f880b'}\n\n````{.cell-code}\n```{{r}}\n#| layout-ncol: 2\n\ntheme_set(my_theme)\ntheme_update(\n  plot.title = ggtext::element_markdown(),\n  plot.caption = ggtext::element_markdown(),\n  axis.title.x = ggtext::element_markdown(),\n  axis.title.y = ggtext::element_markdown(),\n  legend.title = ggtext::element_markdown()\n)\n\ngg1b + theme(legend.position = \"top\")\n\n#ggsave(\"06a_legend_position.pdf\", width = 9, height = 8, device = cairo_pdf)\n\ngg1b + \n  theme(legend.position = \"top\") +\n  guides(color = guide_colorbar(title.position = \"top\", \n                                title.hjust = .5, \n                                barwidth = unit(20, \"lines\"), \n                                barheight = unit(.5, \"lines\")))\n```\n````\n\n::: {.cell-output-display}\n![](index_files/figure-html/unnamed-chunk-32-1.png){width=2100}\n:::\n\n::: {.cell-output-display}\n![](index_files/figure-html/unnamed-chunk-32-2.png){width=2100}\n:::\n:::\n\n\n### Add Images\n\n\n::: {.cell hash='index_cache/html/unnamed-chunk-33_b5b312a9c0ec2fdd921da5ccc63ddb8e'}\n\n````{.cell-code}\n```{{r}}\n#| cache: true\n\ntheme_set(my_theme)\ntheme_update(\n  plot.title = ggtext::element_markdown(),\n  plot.caption = ggtext::element_markdown(),\n  axis.title.x = ggtext::element_markdown(),\n  axis.title.y = ggtext::element_markdown(),\n  legend.title = ggtext::element_markdown()\n)\n\n## read PNG file from web\npng <- magick::image_read(\"images/culmen_depth.png\")\n\n## turn image into `rasterGrob`\nimg <- grid::rasterGrob(png, interpolate = TRUE)\n\ngg5 <- \n  gg1 + \n  annotation_custom(img, ymin = 18, ymax = 28, \n                    xmin = 58, xmax = 65) +\n  labs(caption = \"Data: Gorman, Williams & Fraser (2014) *PLoS ONE* &bull; Illustration: Allison Horst\")   +\n  coord_cartesian(clip = \"off\") # ensure no clipping of labels near the edge\ngg5\n```\n````\n\n::: {.cell-output-display}\n![](index_files/figure-html/unnamed-chunk-33-1.png){width=2100}\n:::\n:::\n\n\n### Using `{patchwork}`\n\n> The goal of `patchwork` is to make it ridiculously simple to combine\n> separate ggplots into the same graphic. As such it tries to solve the\n> same problem as `gridExtra::grid.arrange()` and `cowplot::plot_grid`\n> but using an API that incites exploration and iteration, and scales to\n> arbitrarily complex layouts.\n\n <https://patchwork.data-imaginist.com/>\n\nLet us make two plots and combine them into a single patchwork plot.\n\n\n::: {.cell hash='index_cache/html/unnamed-chunk-34_dd13697f71b7710712d9fe54190c987c'}\n\n````{.cell-code}\n```{{r}}\ntheme_set(my_theme)\ntheme_update(\n  plot.title = ggtext::element_markdown(),\n  plot.caption = ggtext::element_markdown(),\n  axis.title.x = ggtext::element_markdown(),\n  axis.title.y = ggtext::element_markdown(),\n  legend.title = ggtext::element_markdown()\n)\n\n## calculate bill ratio\npenguins_stats <- penguins %>%\n  mutate(bill_ratio = bill_length_mm / bill_depth_mm) %>%\n  filter(!is.na(bill_ratio))\n\n## create a second chart\ngg6 <-\n  ggplot(penguins_stats,\n         aes(\n           y = bill_ratio,\n           x = species,\n           fill = species,\n           color = species\n         )) + geom_violin() +\n  labs(\n    y = \"Bill ratio\",\n    x = \"Species\",\n    subtitle = \"\",\n    caption = \"Data: Gorman, Williams & Fraser (2014) *PLoS ONE* &bull; Illustration: Allison Horst\"\n  ) +\n  theme(\n    panel.grid.major.x = element_line(linewidth = .35),\n    panel.grid.major.y = element_blank(),\n    axis.text.y = element_text(size = 13),\n    axis.ticks.length = unit(0, \"lines\"),\n    plot.title.position = 'plot',\n    plot.subtitle = element_text(margin = margin(t = 5, b = 10)),\n    plot.margin = margin(10, 25, 10, 25)\n  )\n```\n````\n:::\n\n\nNow to combine both plots into one using simple operators:\n\n> For the special case of putting plots besides each other or on top of\n> each other patchwork provides 2 shortcut operators. `|` will place\n> plots next to each other while `/` will place them on top of each\n> other.\n\nFirst we stack up the graphs side by side:\n\n\n::: {.cell hash='index_cache/html/unnamed-chunk-35_e16dec485c94d935deab17319e55febc'}\n\n````{.cell-code}\n```{{r}}\ntheme_set(my_theme)\ntheme_update(\n  plot.title = ggtext::element_markdown(),\n  plot.caption = ggtext::element_markdown(),\n  axis.title.x = ggtext::element_markdown(),\n  axis.title.y = ggtext::element_markdown(),\n  legend.title = ggtext::element_markdown()\n)\n\n## combine both plots\ngg5 | (gg6 + labs(title = \"Bill Ratios of Brush-Tailed Penguins\",\n                  subtitle = \"Violin Plots of Bill Ration versus species\"))\n```\n````\n\n::: {.cell-output-display}\n![](index_files/figure-html/unnamed-chunk-35-1.png){width=2100}\n:::\n:::\n\n\nWe can place them in one column:\n\n\n::: {.cell hash='index_cache/html/unnamed-chunk-36_70857052ebe9b311e99017761f462475'}\n\n````{.cell-code}\n```{{r}}\ntheme_set(my_theme)\ntheme_update(\n  plot.title = ggtext::element_markdown(),\n  plot.caption = ggtext::element_markdown(),\n  axis.title.x = ggtext::element_markdown(),\n  axis.title.y = ggtext::element_markdown(),\n  legend.title = ggtext::element_markdown()\n)\n\ngg5 / (gg6 + labs(title = \"Bill Ratios of Brush-Tailed Penguins\",\n                  subtitle = \"Violin Plots of Bill Ration versus species\")) +\n  plot_layout(heights = c(0.4, 0.4))\n```\n````\n\n::: {.cell-output-display}\n![](index_files/figure-html/unnamed-chunk-36-1.png){width=2100}\n:::\n:::\n\n\n\n## References\n\n::: {#refs style=\"font-size: 60%;\"}\n\\\n1.  Thomas Lin Pedersen, <https://www.data-imaginist.com/>. The creator\n    of `ggforce`, and `patchwork` packages.\\\n2.  Claus Wilke, *cowplot -- Streamlined plot theme and plot annotations\n    for ggplot2*, <https://wilkelab.org/cowplot/index.html>\\\n3.  Claus Wilke, *Spruce up your ggplot2 visualizations with formatted\n    text*, <https://clauswilke.com/talk/rstudio_conf_2020/>. Slides,\n    Code, and Video !\\\n4.  Robert Kabacoff, *ggplot theme cheatsheet*,\n    <https://rkabacoff.github.io/datavis/modifyingthemes.pdf>\\\n5.  Zuguang Gu, *Circular Visualization in R*, <https://jokergoo.github.io/circlize_book/book/>\\\n\n###### {{< iconify lucide package-check >}} R Package Citations\n\n\n::: {.cell hash='index_cache/html/unnamed-chunk-37_bff8ad1050fba67edb3616d812cb26fb'}\n::: {.cell-output-display}\nPackage       Version   Citation     \n------------  --------  -------------\nggdist        3.3.0     @ggdist      \nggforce       0.4.1     @ggforce     \nggtext        0.1.2     @ggtext      \ngrid          4.3.2     @grid        \nmagick        2.8.1     @magick      \npaletteer     1.5.0     @paletteer   \npatchwork     1.1.3     @patchwork   \nscico         1.5.0     @scico       \nshowtext      0.9.6     @showtext    \nsysfonts      0.8.8     @sysfonts    \nsystemfonts   1.0.5     @systemfonts\n:::\n:::\n\n:::\n",
    "supporting": [],
    "filters": [
      "rmarkdown/pagebreak.lua"
    ],
    "includes": {
      "include-in-header": [
        "<link href=\"../../../../../site_libs/pagedtable-1.1/css/pagedtable.css\" rel=\"stylesheet\" />\r\n<script src=\"../../../../../site_libs/pagedtable-1.1/js/pagedtable.js\"></script>\r\n"
      ]
    },
    "engineDependencies": {},
    "preserve": {},
    "postProcess": true
  }
}